mel_fbank_tc/stim_fbank.v
//----------------------------------------------------------------------
// Test Stimuli for MEL_FBANK
//----------------------------------------------------------------------

initial begin : STIM
    wait (rst_n == 1);
    wait (rst_n == 1); // ensure reset asserted
    repeat(10) @(posedge clk);

    fork
        begin : FFT_BIN_FEED
            integer i;
            // Feed 257 FFT bins sequentially using generated random Q1.15 values
            for (i = 0; i < 257; i = i + 1) begin
                @(posedge clk);
                fft_bin_idx = i;
                fft_bin_vld = 1;
                fft_bin = fft_bin_mem[i];  // Use pre-loaded random FFT bin values
            end
            fft_bin_vld = 0;
        end
        begin : MEL_SPEC_CAPTURE
            // Capture mel_spec outputs for 300 cycles
            integer n;
            n = 0;
            while (n < 300) begin
                @(posedge clk);
                if (mel_spec_vld) begin
                    $fdisplay(1, "%0d %h", $time, mel_spec);
                end
                n = n + 1;
            end
        end
    join

    repeat(10) @(posedge clk);
    $finish;
end

initial begin : TIMEOUT
    repeat(10000) #10; // timeout
    $display("[FAILED] MEL_FBANK simulation timed out.");
    $finish;
end

Multiply_qx.v
//----------------------------------------------------------------------
//  Multiply_qx: Complex Multiplier with configurable Q-format
//----------------------------------------------------------------------
module Multiply_qx #(
    parameter   WIDTH_A = 16,
    parameter   Q_A = 15,
    parameter   WIDTH_B = 16,
    parameter   Q_B = 15,
    parameter   WIDTH_C = 16,
    parameter   Q_C = 15
)(
    input   signed  [WIDTH_A-1:0] a_re,
    input   signed  [WIDTH_A-1:0] a_im,
    input   signed  [WIDTH_B-1:0] b_re,
    input   signed  [WIDTH_B-1:0] b_im,
    output  signed  [WIDTH_C-1:0] c_re,
    output  signed  [WIDTH_C-1:0] c_im
);

localparam SHIFT_BITS = Q_A + Q_B - Q_C;
localparam PROD_WIDTH = WIDTH_A + WIDTH_B;

wire signed [PROD_WIDTH-1:0]   arbr, arbi, aibr, aibi;
wire signed [PROD_WIDTH-1:0]   shifted_arbr, shifted_arbi, shifted_aibr, shifted_aibi;
wire signed [PROD_WIDTH-1:0]   sum_re, sum_im;

//  Signed Multiplication
assign  arbr = a_re * b_re;
assign  arbi = a_re * b_im;
assign  aibr = a_im * b_re;
assign  aibi = a_im * b_im;

//  Scaling to output Q format
//  Arithmetic shift right to preserve sign
assign  shifted_arbr = arbr >>> SHIFT_BITS;
assign  shifted_arbi = arbi >>> SHIFT_BITS;
assign  shifted_aibr = aibr >>> SHIFT_BITS;
assign  shifted_aibi = aibi >>> SHIFT_BITS;

//  Sub/Add for complex multiplication result
assign  sum_re = shifted_arbr - shifted_aibi;
assign  sum_im = shifted_arbi + shifted_aibr;

//  Assign to output, truncating/extending as needed
assign  c_re = sum_re;
assign  c_im = sum_im;

/*
Example Verification for Mel Filter Bank Application:
This example demonstrates multiplying a power spectrum value with a mel filter bank weight.
Both values are real, so we will use the complex multiplier by setting the imaginary parts to zero.

Let's assume the following parameters for Q1.15 format:
    parameter   WIDTH_A = 16, Q_A = 15,  // Power Spectrum Value (real)
    parameter   WIDTH_B = 16, Q_B = 15,  // Mel Filter Weight (real)
    parameter   WIDTH_C = 16, Q_C = 15   // Output accumulator value

And the following inputs:
    // Power spectrum value from FFT, assumed to be scaled to [0, 1)
    a_re = 0.5 (decimal) -> 0.5 * 2^15 = 16384 (Q16.15 integer: 0x4000)
    a_im = 0.0 (decimal) -> 0 (Q16.15 integer: 0x0000)

    // Mel filter bank weight, which is always in [0, 1]
    b_re = 0.8 (decimal) -> 0.8 * 2^15 = 26214 (Q16.15 integer: 0x6666)
    b_im = 0.0 (decimal) -> 0 (Q16.15 integer: 0x0000)

Expected multiplication result in floating point:
    c = a * b = (0.5 + j*0.0) * (0.8 + j*0.0)
    c_re = 0.5 * 0.8 = 0.4
    c_im = 0.0

Now let's follow the module's fixed-point arithmetic:
1.  Intermediate product width:
    PROD_WIDTH = WIDTH_A + WIDTH_B = 16 + 16 = 32

2.  Signed Multiplication (results are in Q(16+16).(15+15) = Q32.30 format):
    arbr = a_re * b_re = 16384 * 26214 = 4294836224
    arbi = a_re * b_im = 16384 * 0 = 0
    aibr = a_im * b_re = 0 * 26214 = 0
    aibi = a_im * b_im = 0 * 0 = 0

3.  Scaling to output Q format:
    SHIFT_BITS = Q_A + Q_B - Q_C = 15 + 15 - 15 = 15
    The results are shifted right by 15 bits to convert from Q32.30 to Q32.15.
    shifted_arbr = 4294836224 >>> 15 = 13106.8 -> 13107 (due to rounding/truncation, Verilog `>>>` truncates)
    Let's use precise division: 4294836224 / 32768 = 13107.2. The integer part is 13107.
    shifted_arbi = 0 >>> 15 = 0
    shifted_aibr = 0 >>> 15 = 0
    shifted_aibi = 0 >>> 15 = 0

4.  Sub/Add for complex multiplication result (results are in Q32.15):
    sum_re = shifted_arbr - shifted_aibi = 13107 - 0 = 13107
    sum_im = shifted_arbi + shifted_aibr = 0 + 0 = 0

5.  Assign to output (truncating from Q32.15 to Q16.15):
    c_re = 13107 (Q16.15 integer: 0x3333)
    c_im = 0 (Q16.15 integer: 0x0000)

    Let's convert the result back to decimal to verify:
    c_re (decimal) = 13107 / 2^15 = 13107 / 32768 = 0.399993896...
    This is very close to the expected 0.4. The small difference is due to the quantization of the input `b_re`.
    (0.8 is a repeating fraction in binary, 26214/32768 is the Q15 approximation).

This example verifies that the module correctly performs multiplication for the Q1.15 format used in the mel filter bank calculation.
*/

endmodule

Mel_mac.v
//----------------------------------------------------------------------
//  Mel_mac: Multiply-Accumulate for Mel Filter Bank
//----------------------------------------------------------------------
module MEL_MAC #(
    parameter   WIDTH = 16,
    parameter   Q = 15,
    // Accumulator width needs to be larger to prevent overflow.
    // A single product is Q1.15. Summing up to N_FFT/2 (256) of these
    // requires at least 8 extra integer bits (2^8 = 256).
    // ACC_WIDTH = 1 (sign) + 8 (integer) + 15 (fractional) = 24.
    // Let's use a wider accumulator for safety.
    parameter   ACC_WIDTH = 32,
    parameter   OUT_WIDTH = 16
)(
    input   clk,
    input   rst_n,
    input   clear,  // Synchronous clear for the accumulator
    input   en,     // Enable for the MAC operation

    // Inputs to the multiplier
    input   signed [WIDTH-1:0] a, // Power spectrum value (real, Q1.15)
    input   signed [WIDTH-1:0] b, // Mel filter weight (real, Q1.15)

    // Accumulated output
    output  reg signed [ACC_WIDTH-1:0] c,

    // Automatically scaled output (block floating-point, Usually Not used)
    output  reg signed [OUT_WIDTH-1:0] c_mantissa, // Scaled mantissa
    output  reg [4:0] c_exponent                  // Headroom/Exponent
);

    // Wire for the product of a and b
    wire signed [WIDTH-1:0] product;

    // Instantiate the Q-format multiplier
    Multiply_qx #(
        .WIDTH_A(WIDTH), 
        .Q_A(Q),
        .WIDTH_B(WIDTH), 
        .Q_B(Q),
        .WIDTH_C(WIDTH), 
        .Q_C(Q)
    ) mac_multiplier (
        .a_re(a), 
        .a_im(16'b0),
        .b_re(b), 
        .b_im(16'b0),
        .c_re(product), 
        .c_im()
    );

    // Accumulator logic
    always @(posedge clk or negedge rst_n) begin
        if (!rst_n) begin
            c <= 0;
        end else begin
            case ({clear, en})
                2'b00: c        <= c;
                2'b01: c        <= c + {{ACC_WIDTH-WIDTH{product[WIDTH-1]}}, product};
                2'b10: c        <= 0;
                2'b11: c        <= product; // Clear and add current product
                default: c      <= c;
            endcase
        end
    end

    // --- Automatic Scaling (Block Floating-Point) ---

    // 1. Find the number of leading sign bits (headroom) in the accumulator
    // This is a priority encoder that finds the first bit that differs from the sign bit.
    integer i;
    // Temporary variables for synthesizable headroom computation
    reg found;                     // flag: have we seen the first differing bit?
    reg [4:0] tmp_exponent;        // temporary exponent (width matches c_exponent)

    always @(*) begin: find_exponent
        reg sign_bit;
        sign_bit = c[ACC_WIDTH-1];
        tmp_exponent = 0; // Default for c = 0 or c = -1
        found = 1'b0;
        // Count leading sign-equal bits until the first differing bit is encountered
        for (i = ACC_WIDTH - 2; i >= 0; i = i - 1) begin
            if (!found) begin
                if (c[i] == sign_bit) begin
                    tmp_exponent = tmp_exponent + 1;
                end else begin
                    found = 1'b1; // stop counting further
                end
            end
        end
        c_exponent = tmp_exponent;
    end

    // 2. Scale the output based on the exponent to produce the mantissa
    // This normalizes the accumulator value to fit into the output width.
    always @(*) begin: scale_output
        reg signed [ACC_WIDTH-1:0] shifted_c;
        // We shift left to bring the MSB of the data to the top of the word,
        // preserving the sign bit. This maximizes precision.
        shifted_c = c << c_exponent;
        // Take the top N bits for the mantissa
        c_mantissa = shifted_c[ACC_WIDTH-1 -: OUT_WIDTH];
    end

endmodule

Mel_fbank.v
module MEL_FBANK #(
    
    parameter WIDTH = 16,
    parameter N_MEL = 40,
    parameter N_FFT = 512,
    parameter NZ_MEL_SRAM_DEPTH = 257 // Number of non-zero entries in mel filter bank
)(
    input clk, 
    input rst_n,
    input fft_bin_vld,
    input [WIDTH-1:0] fft_bin,
    input [2*WIDTH-1:0] mel_fbank_weight,
   
    input [1:0] mac_bits,
    output reg mel_spec_vld,
    output reg [WIDTH-1:0] mel_spec,
    output reg [7:0] mel_cnt
);

    
    wire mac_1_bit = mac_bits[1]; 
    wire mac_2_bit = mac_bits[0];
    reg  mac_1_bit_d1;
    reg  mac_2_bit_d1;

    wire mel_mac_1_xor = mac_1_bit ^ mac_1_bit_d1;
    wire mel_mac_2_xor = mac_2_bit ^ mac_2_bit_d1;
    
    reg mel_mac_1_clear;
    reg mel_mac_2_clear;

    always @(posedge clk or negedge rst_n) begin
        if (!rst_n) begin
            mel_mac_1_clear <= 0;
            mel_mac_2_clear <= 0;
            mel_cnt <= 0;
        end else begin
            mel_mac_1_clear <= mel_mac_1_xor;
            mel_mac_2_clear <= mel_mac_2_xor;
            mel_cnt <= mel_spec_vld ? mel_cnt + 1 : mel_cnt;
        end
    end
    
    
    wire [WIDTH-1:0] mel_fbank_weight_1 = mel_fbank_weight[WIDTH-1:0];
    wire [WIDTH-1:0] mel_fbank_weight_2 = mel_fbank_weight[2*WIDTH-1:WIDTH];
    wire [WIDTH-1:0] mel_spec_accum;
    wire [WIDTH-1:0] mel_spec_accum_2;

    always @(*) begin
        case ({mel_mac_1_xor, mel_mac_2_xor})
            2'b00: mel_spec = 0; // No clear, output zero
            2'b01: mel_spec = mel_spec_accum_2;
            2'b10: mel_spec = mel_spec_accum;
            2'b11: mel_spec = 0; // Both cleared, output zero 
            default: mel_spec = 0;
        endcase

        case ({mel_mac_1_xor, mel_mac_2_xor})
            2'b00: mel_spec_vld = 1'b0; // No clear, output invalid
            2'b01: mel_spec_vld = 1'b1;
            2'b10: mel_spec_vld = 1'b1;
            2'b11: mel_spec_vld = 1'b0; // Both cleared, output invalid
            default: mel_spec_vld = 1'b0;
        endcase
    end 

    // clear the mac once clear bit is inverted: XOR operation
    always @(posedge clk or negedge rst_n) begin
        if (!rst_n) begin
            mac_1_bit_d1 <= 0;
            mac_2_bit_d1 <= 1;
        end else begin
            mac_1_bit_d1 <= mac_1_bit;
            mac_2_bit_d1 <= mac_2_bit;
        end
    end

    MEL_MAC #(
        .WIDTH(WIDTH), .Q(15)
    ) MEL_MAC_1 (
        .clk                (clk                ),
        .rst_n              (rst_n              ),
        .clear              (mel_mac_1_xor    ), // Clear at the start of each new frame
        .en                 (fft_bin_vld        ),
        .a                  (fft_bin            ),
        .b                  (mel_fbank_weight_1),
        .c                  (mel_spec_accum     ),
        .c_mantissa         (),
        .c_exponent         ()
    );

    MEL_MAC #(
        .WIDTH(WIDTH), .Q(15)
    ) MEL_MAC_2 (
        .clk                (clk                ),
        .rst_n              (rst_n              ),
        .clear              (mel_mac_2_xor      ), // Clear at the start of each new frame
        .en                 (fft_bin_vld        ),
        .a                  (fft_bin            ),
        .b                  (mel_fbank_weight_2 ),
        .c                  (mel_spec_accum_2   ),
        .c_mantissa         (),
        .c_exponent         ()
    );


endmodule

mel_fbank_tc/tb_Mel_fbank.v
`timescale 1ns / 1ps

module tb_Mel_fbank;

    // Parameters
    parameter WIDTH = 16;
    parameter N_MEL = 40;
    parameter N_FFT = 512;
    parameter NZ_MEL_SRAM_DEPTH = 257;
    parameter CLK_PERIOD = 10; // 100MHz clock

    // Testbench signals
    reg clk;
    reg rst_n;
    reg fft_bin_vld;
    reg [WIDTH-1:0] fft_bin;
    reg [8:0] fft_bin_idx;
    
    wire mel_spec_vld;
    wire [WIDTH-1:0] mel_spec;
    wire [7:0] mel_cnt;
    
    // Internal signals for ROM and SRAM
    wire [1:0] mac_bits;
    wire [2*WIDTH-1:0] mel_fbank_weight;

    // Clock generation
    initial begin
        clk = 0;
        forever #(CLK_PERIOD/2) clk = ~clk;
    end


    // Load change indicator directly from file
    reg [1:0] mac_bits_mem [0:NZ_MEL_SRAM_DEPTH-1];

    initial begin
        $readmemb("D:\\Desktop\\PG Repo\\MEL\\mel_fbank_tc\\convert\\mac_bits.txt", mac_bits_mem);
        $display("Loaded mac_bits from mac_bits.txt");
        // Debug: Display first few values
        $display("DEBUG: mac_bits_mem[0] = %b", mac_bits_mem[0]);
        $display("DEBUG: mac_bits_mem[3] = %b", mac_bits_mem[3]);
        $display("DEBUG: mac_bits_mem[4] = %b", mac_bits_mem[4]);
        $display("DEBUG: mac_bits_mem[10] = %b", mac_bits_mem[10]);
    end


    assign mac_bits = mac_bits_mem[fft_bin_idx];


    // SRAM for mel filterbank weights
    reg [2*WIDTH-1:0] mel_fbank_mem [0:NZ_MEL_SRAM_DEPTH-1];
    
    // Random Q1.15 FFT bin values
    reg [WIDTH-1:0] fft_bin_mem [0:NZ_MEL_SRAM_DEPTH-1];
    
    // Load mel filterbank values from file
    initial begin
        $readmemh("D:\\Desktop\\PG Repo\\MEL\\mel_fbank_tc\\convert\\mac_q15_hex.txt", mel_fbank_mem);
        $display("Loaded mel filterbank weights from mac_q15_hex.txt");
        
        // Load random Q1.15 FFT bin values
        $readmemh("D:\\Desktop\\PG Repo\\MEL\\mel_fbank_tc\\random_fft_bins_q15.txt", fft_bin_mem);
        $display("Loaded random Q1.15 FFT bin values from random_fft_bins_q15.txt");
    end
    
    // SRAM read operation - COMBINATIONAL (no delay)
    assign mel_fbank_weight = (fft_bin_idx < NZ_MEL_SRAM_DEPTH) ? 
                                mel_fbank_mem[fft_bin_idx] : 32'h0;

    // DUT instantiation
    MEL_FBANK #(
        .WIDTH(WIDTH),
        .N_MEL(N_MEL),
        .N_FFT(N_FFT),
        .NZ_MEL_SRAM_DEPTH(NZ_MEL_SRAM_DEPTH)
    ) dut (
        .clk(clk),
        .rst_n(rst_n),
        .fft_bin_vld(fft_bin_vld),
        .fft_bin(fft_bin),
        .mel_fbank_weight(mel_fbank_weight),
        .mac_bits(mac_bits),
        .mel_spec_vld(mel_spec_vld),
        .mel_spec(mel_spec),
        .mel_cnt(mel_cnt)
    );

    // Test stimulus
    integer i;
    integer output_file;
    
    initial begin
        // Initialize signals
        rst_n = 0;
        fft_bin_vld = 0;
        fft_bin = 0;
        fft_bin_idx = 0;
        
        // Open output file for writing
        output_file = $fopen("mel_output.txt", "w");
        if (output_file == 0) begin
            $display("ERROR: Could not open output.txt for writing");
            $finish;
        end
        
        // VCD dump for waveform viewing
        $dumpfile("tb_Mel_fbank.vcd");
        $dumpvars(0, tb_Mel_fbank);
        
        // Reset
        #(CLK_PERIOD*5);
        rst_n = 1;
        #(CLK_PERIOD*2);
        
        $display("\n=== Starting MEL_FBANK Test ===\n");
        $display("Time\t\tIdx\tFFT_Bin\t\tMAC_Bits\tWeight[31:16]\tWeight[15:0]\tMel_Spec\tVld");
        $display("-------------------------------------------------------------------------------------------");
        
        // Test: Feed FFT bins through the filterbank
        for (i = 0; i < 257; i = i + 1) begin
            @(posedge clk);
            fft_bin_idx = i;
            fft_bin_vld = 1;
            fft_bin = fft_bin_mem[i]; // Use random Q1.15 values from memory
            
            #1; // Small delay for signal propagation before display
            $display("%0t\t%d\t%h\t%b\t\t%h\t%h\t%h\t%b",
                     $time, fft_bin_idx, fft_bin, mac_bits, 
                     mel_fbank_weight[31:16], mel_fbank_weight[15:0],
                     mel_spec, mel_spec_vld);
            
            // Additional debug for indices where we expect 11
            if (i == 3 || i == 4 || i == 10 || i == 11 || i == 12) begin
                $display("  -> DEBUG idx=%d: mac_bits_mem[%d]=%b, mac_bits=%b", 
                         i, i, mac_bits_mem[i], mac_bits);
            end
        end
        
        // Continue for a few more cycles to see final outputs
        fft_bin_vld = 0;
        repeat(10) @(posedge clk);
        
        // Close output file
        $fclose(output_file);
        
        $display("\n=== Test Completed ===\n");
        $display("Output written to mel_output.txt");
        $finish;
    end
    
    // Monitor for valid mel spectrum outputs
    always @(posedge clk) begin
        if (mel_spec_vld && mel_cnt < N_MEL) begin
            $display("*** Valid Mel Spectrum Output [%0d]: %h at time %0t", mel_cnt, mel_spec, $time);
            // Write to output file only until we reach N_MEL outputs
            $fwrite(output_file, "%h\n", mel_spec);
        end else if (mel_spec_vld && mel_cnt >= N_MEL) begin
            $display("*** Mel Spectrum Output [%0d] (not recorded - exceeded N_MEL): %h at time %0t", mel_cnt, mel_spec, $time);
        end
    end
    // Timeout watchdog
    initial begin
        #100000; // 100us timeout
        $display("ERROR: Simulation timeout!");
        $finish;
    end


// Include external stimuli/logger
`include "stim_fbank.v"

endmodule

mel_fbank_tc/tb_Mel_fbank.vcd
$date
	Wed Oct 22 20:28:45 2025
$end
$version
	Icarus Verilog
$end
$timescale
	1ps
$end
$scope module tb_Mel_fbank $end
$var wire 2 ! mac_bits [1:0] $end
$var wire 1 " mel_spec_vld $end
$var wire 16 # mel_spec [15:0] $end
$var wire 32 $ mel_fbank_weight [31:0] $end
$var wire 8 % mel_cnt [7:0] $end
$var parameter 32 & CLK_PERIOD $end
$var parameter 32 ' NZ_MEL_SRAM_DEPTH $end
$var parameter 32 ( N_FFT $end
$var parameter 32 ) N_MEL $end
$var parameter 32 * WIDTH $end
$var reg 1 + clk $end
$var reg 16 , fft_bin [15:0] $end
$var reg 9 - fft_bin_idx [8:0] $end
$var reg 1 . fft_bin_vld $end
$var reg 1 / rst_n $end
$var integer 32 0 i [31:0] $end
$var integer 32 1 output_file [31:0] $end
$scope module dut $end
$var wire 1 + clk $end
$var wire 16 2 fft_bin [15:0] $end
$var wire 1 . fft_bin_vld $end
$var wire 2 3 mac_bits [1:0] $end
$var wire 32 4 mel_fbank_weight [31:0] $end
$var wire 1 5 mel_mac_1_xor $end
$var wire 1 6 mel_mac_2_xor $end
$var wire 1 / rst_n $end
$var wire 16 7 mel_spec_accum_2 [15:0] $end
$var wire 16 8 mel_spec_accum [15:0] $end
$var wire 16 9 mel_fbank_weight_2 [15:0] $end
$var wire 16 : mel_fbank_weight_1 [15:0] $end
$var wire 1 ; mac_2_bit $end
$var wire 1 < mac_1_bit $end
$var parameter 32 = NZ_MEL_SRAM_DEPTH $end
$var parameter 32 > N_FFT $end
$var parameter 32 ? N_MEL $end
$var parameter 32 @ WIDTH $end
$var reg 1 A mac_1_bit_d1 $end
$var reg 1 B mac_2_bit_d1 $end
$var reg 8 C mel_cnt [7:0] $end
$var reg 1 D mel_mac_1_clear $end
$var reg 1 E mel_mac_2_clear $end
$var reg 16 F mel_spec [15:0] $end
$var reg 1 " mel_spec_vld $end
$scope module MEL_MAC_1 $end
$var wire 16 G a [15:0] $end
$var wire 16 H b [15:0] $end
$var wire 1 5 clear $end
$var wire 1 + clk $end
$var wire 1 . en $end
$var wire 1 / rst_n $end
$var wire 16 I product [15:0] $end
$var parameter 32 J ACC_WIDTH $end
$var parameter 32 K OUT_WIDTH $end
$var parameter 32 L Q $end
$var parameter 32 M WIDTH $end
$var reg 32 N c [31:0] $end
$var reg 5 O c_exponent [4:0] $end
$var reg 16 P c_mantissa [15:0] $end
$var reg 1 Q found $end
$var reg 5 R tmp_exponent [4:0] $end
$var integer 32 S i [31:0] $end
$scope module mac_multiplier $end
$var wire 16 T a_im [15:0] $end
$var wire 16 U a_re [15:0] $end
$var wire 16 V b_im [15:0] $end
$var wire 16 W b_re [15:0] $end
$var wire 32 X sum_re [31:0] $end
$var wire 32 Y sum_im [31:0] $end
$var wire 32 Z shifted_arbr [31:0] $end
$var wire 32 [ shifted_arbi [31:0] $end
$var wire 32 \ shifted_aibr [31:0] $end
$var wire 32 ] shifted_aibi [31:0] $end
$var wire 16 ^ c_re [15:0] $end
$var wire 16 _ c_im [15:0] $end
$var wire 32 ` arbr [31:0] $end
$var wire 32 a arbi [31:0] $end
$var wire 32 b aibr [31:0] $end
$var wire 32 c aibi [31:0] $end
$var parameter 33 d PROD_WIDTH $end
$var parameter 32 e Q_A $end
$var parameter 32 f Q_B $end
$var parameter 32 g Q_C $end
$var parameter 34 h SHIFT_BITS $end
$var parameter 32 i WIDTH_A $end
$var parameter 32 j WIDTH_B $end
$var parameter 32 k WIDTH_C $end
$upscope $end
$scope begin find_exponent $end
$var reg 1 l sign_bit $end
$upscope $end
$scope begin scale_output $end
$var reg 32 m shifted_c [31:0] $end
$upscope $end
$upscope $end
$scope module MEL_MAC_2 $end
$var wire 16 n a [15:0] $end
$var wire 16 o b [15:0] $end
$var wire 1 6 clear $end
$var wire 1 + clk $end
$var wire 1 . en $end
$var wire 1 / rst_n $end
$var wire 16 p product [15:0] $end
$var parameter 32 q ACC_WIDTH $end
$var parameter 32 r OUT_WIDTH $end
$var parameter 32 s Q $end
$var parameter 32 t WIDTH $end
$var reg 32 u c [31:0] $end
$var reg 5 v c_exponent [4:0] $end
$var reg 16 w c_mantissa [15:0] $end
$var reg 1 x found $end
$var reg 5 y tmp_exponent [4:0] $end
$var integer 32 z i [31:0] $end
$scope module mac_multiplier $end
$var wire 16 { a_im [15:0] $end
$var wire 16 | a_re [15:0] $end
$var wire 16 } b_im [15:0] $end
$var wire 16 ~ b_re [15:0] $end
$var wire 32 !" sum_re [31:0] $end
$var wire 32 "" sum_im [31:0] $end
$var wire 32 #" shifted_arbr [31:0] $end
$var wire 32 $" shifted_arbi [31:0] $end
$var wire 32 %" shifted_aibr [31:0] $end
$var wire 32 &" shifted_aibi [31:0] $end
$var wire 16 '" c_re [15:0] $end
$var wire 16 (" c_im [15:0] $end
$var wire 32 )" arbr [31:0] $end
$var wire 32 *" arbi [31:0] $end
$var wire 32 +" aibr [31:0] $end
$var wire 32 ," aibi [31:0] $end
$var parameter 33 -" PROD_WIDTH $end
$var parameter 32 ." Q_A $end
$var parameter 32 /" Q_B $end
$var parameter 32 0" Q_C $end
$var parameter 34 1" SHIFT_BITS $end
$var parameter 32 2" WIDTH_A $end
$var parameter 32 3" WIDTH_B $end
$var parameter 32 4" WIDTH_C $end
$upscope $end
$scope begin find_exponent $end
$var reg 1 5" sign_bit $end
$upscope $end
$scope begin scale_output $end
$var reg 32 6" shifted_c [31:0] $end
$upscope $end
$upscope $end
$upscope $end
$scope begin STIM $end
$scope begin FFT_BIN_FEED $end
$var integer 32 7" i [31:0] $end
$upscope $end
$scope begin MEL_SPEC_CAPTURE $end
$var integer 32 8" n [31:0] $end
$upscope $end
$upscope $end
$scope begin TIMEOUT $end
$upscope $end
$upscope $end
$enddefinitions $end
$comment Show the parameter values. $end
$dumpall
b10000 4"
b10000 3"
b10000 2"
b1111 1"
b1111 0"
b1111 /"
b1111 ."
b100000 -"
b10000 t
b1111 s
b10000 r
b100000 q
b10000 k
b10000 j
b10000 i
b1111 h
b1111 g
b1111 f
b1111 e
b100000 d
b10000 M
b1111 L
b10000 K
b100000 J
b10000 @
b101000 ?
b1000000000 >
b100000001 =
b10000 *
b101000 )
b1000000000 (
b100000001 '
b1010 &
$end
#0
$dumpvars
bx 8"
bx 7"
b0 6"
05"
b0 ,"
b0 +"
b0 *"
b0 )"
b0 ("
b0 '"
b0 &"
b0 %"
b0 $"
b0 #"
b0 ""
b0 !"
b0 ~
b0 }
b0 |
b0 {
b11111111111111111111111111111111 z
b11111 y
0x
b0 w
b11111 v
b0 u
b0 p
b0 o
b0 n
b0 m
0l
b0 c
b0 b
b0 a
b0 `
b0 _
b0 ^
b0 ]
b0 \
b0 [
b0 Z
b0 Y
b0 X
b0 W
b0 V
b0 U
b0 T
b11111111111111111111111111111111 S
b11111 R
0Q
b0 P
b11111 O
b0 N
b0 I
b0 H
b0 G
b0 F
0E
0D
b0 C
1B
0A
0<
1;
b0 :
b0 9
b0 8
b0 7
06
05
b0 4
b1 3
b0 2
b10000000000000000000000000000011 1
bx 0
0/
0.
b0 -
b0 ,
0+
b0 %
b0 $
b0 #
0"
b1 !
$end
#5000
1+
#10000
0+
#15000
1+
#20000
0+
#25000
1+
#30000
0+
#35000
1+
#40000
0+
#45000
1+
#50000
0+
1/
#55000
1+
#60000
0+
#65000
1+
#70000
0+
b0 0
#75000
b10001110110001 ,
b10001110110001 2
b10001110110001 G
b10001110110001 U
b10001110110001 n
b10001110110001 |
1.
1+
#76000
b1 0
#80000
0+
#85000
b1010101001011101 p
b1010101001011101 '"
b11111111111111111010101001011101 !"
b11111111111111111010101001011101 #"
b11010101001011101010001011100011 )"
b101101000100101 9
b101101000100101 o
b101101000100101 ~
b1011010001001010000000000000000 $
b1011010001001010000000000000000 4
b1000011001100111 ,
b1000011001100111 2
b1000011001100111 G
b1000011001100111 U
b1000011001100111 n
b1000011001100111 |
b1 -
1+
#86000
b10 0
#90000
0+
#95000
b1010101001011101 w
b10101010010111010000000000000000 6"
b10000 v
1x
b11111111111111111111111111111111 z
b10000 y
15"
b1010101001011101 7
b11111111111111111010101001011101 u
b1110100111100000 I
b1110100111100000 ^
b11111111111111111110100111100000 X
b11111111111111111110100111100000 Z
b1101110010000111 p
b1101110010000111 '"
b11110100111100000011101101111000 `
b11000100101011 :
b11000100101011 H
b11000100101011 W
b100111011010101 9
b100111011010101 o
b100111011010101 ~
b11111111111111111101110010000111 !"
b11111111111111111101110010000111 #"
b1001110110101010011000100101011 $
b1001110110101010011000100101011 4
b11101110010000111100010010001000 )"
b1100011001101000 ,
b1100011001101000 2
b1100011001101000 G
b1100011001101000 U
b1100011001101000 n
b1100011001101000 |
b10 -
1+
#96000
b11 0
#100000
0+
#105000
b1110100111100000 #
b1110100111100000 F
b1000011011100100 w
b10000110111001000000000000000000 6"
b11111111111111111111111111111111 z
1x
b10000 y
b1000011011100100 7
b1010011110000000 P
b10100111100000000000000000000000 m
b10010 O
1Q
b11111111111111111111111111111111 S
b10010 R
1l
b1110100111100000 8
b11111111111111111000011011100100 u
b11111111111111111110100111100000 N
1"
b1011110000111011 I
b1011110000111011 ^
b1111110011101000 p
b1111110011101000 '"
15
b111101001101011 :
b111101001101011 H
b111101001101011 W
b10110010101 9
b10110010101 o
b10110010101 ~
b11111111111111111011110000111011 X
b11111111111111111011110000111011 Z
b11111111111111111111110011101000 !"
b11111111111111111111110011101000 #"
1<
b101100101010111101001101011 $
b101100101010111101001101011 4
b11011110000111011000101000001100 `
b11111110011101000111010111110100 )"
b1011100100100100 ,
b1011100100100100 2
b1011100100100100 G
b1011100100100100 U
b1011100100100100 n
b1011100100100100 |
b11 !
b11 3
b11 -
1+
#106000
b100 0
#110000
0+
#115000
0"
b0 #
b0 F
b1011110000111011 P
b10111100001110110000000000000000 m
b10000 O
b11111111111111111111111111111111 S
1Q
b10000 R
b1011110000111011 8
b1000001111001100 w
b10000011110011000000000000000000 6"
b11111111111111111111111111111111 z
1x
b10000 y
b1000001111001100 7
05
b11111111111111111011110000111011 N
b11111111111111111000001111001100 u
b1 %
b1 C
1D
1A
b1010000110001 I
b1010000110001 ^
b10100001010111 p
b10100001010111 '"
b10101010110011 :
b10101010110011 H
b10101010110011 W
b101010101001101 9
b101010101001101 o
b101010101001101 ~
b1010000110001 X
b1010000110001 Z
b10100001010111 !"
b10100001010111 #"
b1010101010011010010101010110011 $
b1010101010011010010101010110011 4
b1010000110001100110111001011 `
b10100001010111011001000110101 )"
b11110010001001 ,
b11110010001001 2
b11110010001001 G
b11110010001001 U
b11110010001001 n
b11110010001001 |
b100 -
1+
#116000
b101 0
#120000
0+
#125000
b1010110000100011 w
b10101100001000110000000000000000 6"
b11111111111111111111111111111111 z
1x
b10000 y
b1010110000100011 7
b1010000011011000 P
b10100000110110000000000000000000 m
b10001 O
b11111111111111111111111111111111 S
1Q
b10001 R
b1101000001101100 8
0D
b11111111111111111010110000100011 u
b11111111111111111101000001101100 N
1"
b1010110000100011 #
b1010110000100011 F
b110001001101 I
b110001001101 ^
b10000011101110 p
b10000011101110 '"
16
b10001011001111 :
b10001011001111 H
b10001011001111 W
b101110100110001 9
b101110100110001 o
b101110100110001 ~
b110001001101 X
b110001001101 Z
b10000011101110 !"
b10000011101110 #"
0;
b1011101001100010010001011001111 $
b1011101001100010010001011001111 4
b110001001101000101110000100 `
b10000011101110111010001111100 )"
b10110100111100 ,
b10110100111100 2
b10110100111100 G
b10110100111100 U
b10110100111100 n
b10110100111100 |
b10 !
b10 3
b101 -
1+
#126000
b110 0
#130000
0+
#135000
0"
b0 #
b0 F
b1011100101110010 P
b10111001011100100000000000000000 m
b11111111111111111111111111111111 S
1Q
b10001 R
b1101110010111001 8
b100000111011100 w
b1000001110111000000000000000000 6"
b10001 v
b11111111111111111111111111111111 z
1x
b10001 y
05"
b10000011101110 7
06
b11111111111111111101110010111001 N
b10000011101110 u
b10 %
b10 C
1E
0B
b101011000011010 I
b101011000011010 ^
b111001001011 p
b111001001011 '"
b110110111000110 :
b110110111000110 H
b110110111000110 W
b1001000111010 9
b1001000111010 o
b1001000111010 ~
b101011000011010 X
b101011000011010 Z
b111001001011 !"
b111001001011 #"
b10010001110100110110111000110 $
b10010001110100110110111000110 4
b101011000011010001010011100100 `
b111001001011110101100011100 )"
b110010001100110 ,
b110010001100110 2
b110010001100110 G
b110010001100110 U
b110010001100110 n
b110010001100110 |
b110 -
1+
#136000
b111 0
#140000
0+
