fake_mem.v
module fake_mem_gen#(
    parameter MEM_DEPTH  = 2**32,
    parameter DATA_WIDTH = 8,
    parameter ADDR_WIDTH = $clog2(MEM_DEPTH)
)(
    input                           clk,
    input                           rst_n,
    input                           wr_en,
    input [ADDR_WIDTH-1:0]          program_counter,
    output reg [4*DATA_WIDTH-1:0]     data_out
);
    reg [DATA_WIDTH-1:0] mem [0:MEM_DEPTH-1];   
    initial begin
        $readmemh("fake_mem_init.txt", mem);
    end
    always @(posedge clk or negedge rst_n) begin
        if(!rst_n) begin
            data_out <= {4{8'h00}};
        end else if(wr_en) begin
            data_out <= {mem[program_counter], mem[program_counter+1], mem[program_counter+2], mem[program_counter+3]};
        end
    end
    

endmodule

fake_mem_tc/tb_fake_mem.v
`timescale 1ns / 1ps

//=============================================================================
// Testbench for fake_mem module
// Tests memory read operations with various addresses
//=============================================================================

module tb_fake_mem;

    // Parameters matching the DUT
    localparam MEM_DEPTH  = 256;
    localparam DATA_WIDTH = 8;
    localparam ADDR_WIDTH = 32;
    localparam CLK_PERIOD = 10;

    // Testbench signals
    reg                             clk;
    reg                             rst_n;
    reg                             wr_en;
    reg [ADDR_WIDTH-1:0]           program_counter;
    wire [4*DATA_WIDTH-1:0]        data_out;

    // File handles for logging
    integer output_file;
    integer error_count;
    integer test_count;

    // Instantiate the DUT (Device Under Test)
    fake_mem_gen #(
        .MEM_DEPTH(MEM_DEPTH),
        .DATA_WIDTH(DATA_WIDTH),
        .ADDR_WIDTH(ADDR_WIDTH)
    ) DUT (
        .clk(clk),
        .rst_n(rst_n),
        .wr_en(wr_en),
        .program_counter(program_counter),
        .data_out(data_out)
    );

    // Clock generation
    initial begin
        clk = 0;
        forever #(CLK_PERIOD/2) clk = ~clk;
    end

    // VCD dump for waveform viewing
    initial begin
        $dumpfile("tb_fake_mem.vcd");
        $dumpvars(0, tb_fake_mem);
    end

    // Main test sequence
    initial begin
        // Open output file
        output_file = $fopen("output.txt", "w");
        error_count = 0;
        test_count = 0;

        // Initialize signals
        $display("========================================");
        $display("Starting fake_mem testbench...");
        $display("========================================");
        
        rst_n = 0;
        wr_en = 0;
        program_counter = 0;
        
        // Apply reset
        #(CLK_PERIOD * 5);
        rst_n = 1;
        #(CLK_PERIOD);
        
        $display("Reset released. Starting memory read tests.");
        
        // Test Case 1: Read from various addresses
        $display("\n[Test 1] Reading from sequential addresses...");
        test_read(0);
        test_read(4);
        test_read(8);
        test_read(12);
        test_read(16);
        
        // Test Case 2: Read from mid-range addresses
        $display("\n[Test 2] Reading from mid-range addresses...");
        test_read(32);
        test_read(64);
        test_read(96);
        test_read(128);
        
        // Test Case 3: Read from upper addresses
        $display("\n[Test 3] Reading from upper addresses...");
        test_read(192);
        test_read(252);
        
        // Test Case 4: Test with wr_en disabled
        $display("\n[Test 4] Testing with wr_en disabled...");
        wr_en = 0;
        program_counter = 0;
        #(CLK_PERIOD);
        $display("  PC=%d, wr_en=%b, data_out=0x%08h (should be previous or zero)", 
                 program_counter, wr_en, data_out);
        
        // Test Case 5: Rapid address changes
        $display("\n[Test 5] Testing rapid address changes...");
        wr_en = 1;
        for (integer i = 0; i < 20; i = i + 8) begin
            program_counter = i;
            #(CLK_PERIOD);
            $display("  PC=%3d, data_out=0x%08h", program_counter, data_out);
            $fwrite(output_file, "%08h\n", data_out);
        end
        
        // Summary
        #(CLK_PERIOD * 5);
        $display("\n========================================");
        $display("Testbench completed!");
        $display("Total tests: %0d", test_count);
        if (error_count == 0) begin
            $display("Result: PASS - All tests completed");
        end else begin
            $display("Result: FAIL - %0d errors detected", error_count);
        end
        $display("========================================");
        
        // Close file and finish
        $fclose(output_file);
        $finish;
    end

    // Task to test memory read
    task test_read;
        input [ADDR_WIDTH-1:0] addr;
        begin
            test_count = test_count + 1;
            wr_en = 1;
            program_counter = addr;
            #(CLK_PERIOD);
            $display("  PC=%3d, data_out=0x%08h [%02h %02h %02h %02h]", 
                     program_counter, 
                     data_out,
                     data_out[31:24],
                     data_out[23:16],
                     data_out[15:8],
                     data_out[7:0]);
            $fwrite(output_file, "%08h\n",data_out);
        end
    endtask

    // Timeout watchdog
    initial begin
        #(CLK_PERIOD * 1000);
        $display("\n[ERROR] Testbench timeout!");
        $fclose(output_file);
        $finish;
    end

endmodule

fake_mem_tc/tb_fake_mem.vcd
$date
	Fri Nov 07 19:25:10 2025
$end
$version
	Icarus Verilog
$end
$timescale
	1ps
$end
$scope module tb_fake_mem $end
$var wire 32 ! data_out [31:0] $end
$var parameter 32 " ADDR_WIDTH $end
$var parameter 32 # CLK_PERIOD $end
$var parameter 32 $ DATA_WIDTH $end
$var parameter 32 % MEM_DEPTH $end
$var reg 1 & clk $end
$var reg 8 ' program_counter [7:0] $end
$var reg 1 ( rst_n $end
$var reg 1 ) wr_en $end
$var integer 32 * error_count [31:0] $end
$var integer 32 + output_file [31:0] $end
$var integer 32 , test_count [31:0] $end
$scope module DUT $end
$var wire 1 & clk $end
$var wire 8 - program_counter [7:0] $end
$var wire 1 ( rst_n $end
$var wire 1 ) wr_en $end
$var parameter 32 . ADDR_WIDTH $end
$var parameter 32 / DATA_WIDTH $end
$var parameter 32 0 MEM_DEPTH $end
$var reg 32 1 data_out [31:0] $end
$upscope $end
$scope begin $ivl_for_loop0 $end
$var integer 32 2 i [31:0] $end
$upscope $end
$scope task test_read $end
$var reg 8 3 addr [7:0] $end
$upscope $end
$upscope $end
$enddefinitions $end
$comment Show the parameter values. $end
$dumpall
b100000000 0
b1000 /
b1000 .
b100000000 %
b1000 $
b1010 #
b1000 "
$end
#0
$dumpvars
bx 3
bx 2
b0 1
b0 -
b0 ,
b10000000000000000000000000000011 +
b0 *
0)
0(
b0 '
0&
b0 !
$end
#5000
1&
#10000
0&
#15000
1&
#20000
0&
#25000
1&
#30000
0&
#35000
1&
#40000
0&
#45000
1&
#50000
0&
1(
#55000
1&
#60000
0&
1)
b1 ,
b0 3
#65000
b10000001000000011 !
b10000001000000011 1
1&
#70000
0&
b100 '
b100 -
b10 ,
b100 3
#75000
b100000001010000011000000111 !
b100000001010000011000000111 1
1&
#80000
0&
b1000 '
b1000 -
b11 ,
b1000 3
#85000
b1000000010010000101000001011 !
b1000000010010000101000001011 1
1&
#90000
0&
b1100 '
b1100 -
b100 ,
b1100 3
#95000
b1100000011010000111000001111 !
b1100000011010000111000001111 1
1&
#100000
0&
b10000 '
b10000 -
b101 ,
b10000 3
#105000
b10000000100010001001000010011 !
b10000000100010001001000010011 1
1&
#110000
0&
b100000 '
b100000 -
b110 ,
b100000 3
#115000
b100000001000010010001000100011 !
b100000001000010010001000100011 1
1&
#120000
0&
b1000000 '
b1000000 -
b111 ,
b1000000 3
#125000
b1000000010000010100001001000011 !
b1000000010000010100001001000011 1
1&
#130000
0&
b1100000 '
b1100000 -
b1000 ,
b1100000 3
#135000
b1100000011000010110001001100011 !
b1100000011000010110001001100011 1
1&
#140000
0&
b10000000 '
b10000000 -
b1001 ,
b10000000 3
#145000
b11111111111111101111110111111100 !
b11111111111111101111110111111100 1
1&
#150000
0&
b11000000 '
b11000000 -
b1010 ,
b11000000 3
#155000
b10111111101111101011110110111100 !
b10111111101111101011110110111100 1
1&
#160000
0&
b11111100 '
b11111100 -
b1011 ,
b11111100 3
#165000
b10000011100000101000000110000000 !
b10000011100000101000000110000000 1
1&
#170000
0&
b0 '
b0 -
0)
#175000
1&
#180000
0&
b0 2
1)
#185000
b10000001000000011 !
b10000001000000011 1
1&
#190000
0&
b1000 '
b1000 -
b1000 2
#195000
b1000000010010000101000001011 !
b1000000010010000101000001011 1
1&
#200000
0&
b10000 '
b10000 -
b10000 2
#205000
b10000000100010001001000010011 !
b10000000100010001001000010011 1
1&
#210000
0&
b11000 2
