BitRevReorder.v
//----------------------------------------------------------------------
//  Bit-Reversal Reordering with Ping-Pong Buffer (Register File based)
//  Converts FFT bit-reversed output to natural order.
//  It accepts bit-reversed data and outputs it in natural order.
//----------------------------------------------------------------------
module BRR_PP #(
    parameter N = 128,              // FFT size (must be power of 2)
    parameter BITS = 7,             // log2(N) - address width
    parameter WIDTH = 16            // Data width for real/imag components
)(
    input                   clock,
    input                   reset,
    
    // Input: bit-reversed FFT output
    input                   di_en,
    input  [WIDTH-1:0]      di_re,
    input  [WIDTH-1:0]      di_im,
    
    // Output: natural order
    output reg              do_en,
    output reg [WIDTH-1:0]  do_re,
    output reg [WIDTH-1:0]  do_im
);

//----------------------------------------------------------------------
//  Ping-Pong Dual-Port Register File
//  Buffer A and Buffer B alternate between write and read
//----------------------------------------------------------------------
reg [WIDTH-1:0] bufA_re [0:N-1];
reg [WIDTH-1:0] bufA_im [0:N-1];
reg [WIDTH-1:0] bufB_re [0:N-1];
reg [WIDTH-1:0] bufB_im [0:N-1];

//----------------------------------------------------------------------
//  Control Logic
//----------------------------------------------------------------------
reg                 buf_sel;        // 0: Write to A, Read from B
                                    // 1: Write to B, Read from A
reg [BITS-1:0]      wr_cnt;         // Write counter (sequential)
reg [BITS-1:0]      rd_cnt;         // Read counter (sequential)
reg                 wr_active;      // Write operation active
reg                 rd_active;      // Read operation active
reg                 first_frame;    // Flag to prevent reading before first write is complete

//----------------------------------------------------------------------
//  Bit-Reverse Function
//  Reverses the bit order of the input address
//----------------------------------------------------------------------
function [BITS-1:0] bit_reverse;
    input [BITS-1:0] in;
    integer i;
    begin
        bit_reverse = 0;
        for (i = 0; i < BITS; i = i + 1)
            bit_reverse[i] = in[BITS-1-i];
    end
endfunction

//----------------------------------------------------------------------
//  Address Generation
//  Input is in bit-reversed order. We write to a bit-reversed address
//  so the data is stored in natural order. Reading is done sequentially.
//----------------------------------------------------------------------
wire [BITS-1:0] wr_addr = bit_reverse(wr_cnt);
wire [BITS-1:0] rd_addr = rd_cnt;

//----------------------------------------------------------------------
//  Write Logic - Buffer Switching
//----------------------------------------------------------------------
always @(posedge clock) begin
    if (reset) begin
        wr_cnt <= 0;
        wr_active <= 0;
        buf_sel <= 0;
        first_frame <= 1;
    end else begin
        if (di_en) begin
            wr_active <= 1;
            
            // Write to the currently active write buffer
            if (buf_sel == 0) begin // Write to A
                bufA_re[wr_addr] <= di_re;
                bufA_im[wr_addr] <= di_im;
            end else begin // Write to B
                bufB_re[wr_addr] <= di_re;
                bufB_im[wr_addr] <= di_im;
            end
            
            // Increment write counter and swap buffers when full
            if (wr_cnt == N-1) begin
                wr_cnt <= 0;
                buf_sel <= ~buf_sel;    // Swap buffers for next frame
                first_frame <= 0;       // First frame is now written
                wr_active <= 0;         // Finished writing this frame
            end else begin
                wr_cnt <= wr_cnt + 1;
            end
        end
    end
end

//----------------------------------------------------------------------
//  Read Logic - Buffer Switching
//----------------------------------------------------------------------
always @(posedge clock) begin
    if (reset) begin
        rd_cnt <= 0;
        rd_active <= 0;
        do_en <= 0;
    end else begin
        // Start reading a frame when the other buffer is full
        if (wr_cnt == N-1 && di_en) begin
             rd_active <= 1;
        end

        if (rd_active && !first_frame) begin
            // Read from the inactive write buffer (the one that's full)
            if (buf_sel == 0) begin // Read from B
                do_re <= bufB_re[rd_addr];
                do_im <= bufB_im[rd_addr];
            end else begin // Read from A
                do_re <= bufA_re[rd_addr];
                do_im <= bufA_im[rd_addr];
            end
            do_en <= 1;
            
            // Increment read counter
            if (rd_cnt == N-1) begin
                rd_cnt <= 0;
                rd_active <= 0; // Finished reading frame
                do_en <= 0;
            end else begin
                rd_cnt <= rd_cnt + 1;
            end
        end else begin
            do_en <= 0;
        end
    end
end


////  Read Logic - Sequential Output in Natural Order
////----------------------------------------------------------------------
//reg rd_buf_sel;  // Read buffer selection (opposite of write buffer)

//always @(posedge clock) begin
//    if (reset) begin
//        rd_cnt <= 0;
//        rd_active <= 0;
//        rd_buf_sel <= 1;  // Start reading from opposite buffer
//        do_en <= 0;
//        do_re <= 0;
//        do_im <= 0;
//    end else begin
//        // Start reading when first frame is complete and we're not currently writing to this buffer
//        if (!first_frame && !rd_active) begin
//            rd_active <= 1;
//            rd_cnt <= 0;
//        end
        
//        if (rd_active) begin
//            // Read from the buffer that's not being written to
//            if (rd_buf_sel == 0) begin
//                do_re <= bufA_re[rd_cnt];
//                do_im <= bufA_im[rd_cnt];
//            end else begin
//                do_re <= bufB_re[rd_cnt];
//                do_im <= bufB_im[rd_cnt];
//            end
            
//            do_en <= 1;
            
//            // Increment read counter
//            if (rd_cnt == N-1) begin
//                rd_cnt <= 0;
//                rd_active <= 0;
//                rd_buf_sel <= ~rd_buf_sel;  // Swap read buffer
//            end else begin
//                rd_cnt <= rd_cnt + 1;
//            end
//        end else begin
//            do_en <= 0;
//        end
//    end
//end

//----------------------------------------------------------------------
//  Synthesis Notes:
//  - Total RAM: 2 * N * 2 * WIDTH bits
//  - For N=128, WIDTH=16: 8192 bits (1 KB)
//  - Latency: N clock cycles (one frame delay)
//  - Throughput: Continuous streaming (no gaps after first frame)
//----------------------------------------------------------------------

endmodule

brr_pp_tc/tb_BRR_PP.v
`timescale 1ns / 1ps

module tb_BRR_PP;

    // Parameters
    localparam N = 128;
    localparam BITS = 7;
    localparam WIDTH = 16;
    localparam CLK_PERIOD = 10;

    // Testbench signals
    reg                 clock;
    reg                 reset;
    reg                 di_en;
    reg  [WIDTH-1:0]    di_re;
    reg  [WIDTH-1:0]    di_im;

    wire                do_en;
    wire [WIDTH-1:0]    do_re;
    wire [WIDTH-1:0]    do_im;

    // Instantiate the DUT
    BRR_PP #(
        .N(N),
        .BITS(BITS),
        .WIDTH(WIDTH)
    ) DUT (
        .clock(clock),
        .reset(reset),
        .di_en(di_en),
        .di_re(di_re),
        .di_im(di_im),
        .do_en(do_en),
        .do_re(do_re),
        .do_im(do_im)
    );

    // Clock generation
    always #(CLK_PERIOD/2) clock = ~clock;

    // Stimulus
    initial begin
        // Initialize signals
        clock = 0;
        reset = 1;
        di_en = 0;
        di_re = 0;
        di_im = 0;

        // Reset sequence
        #100;
        reset = 0;
        #100;
        reset = 1;
        
        // Wait for reset to propagate
        @(posedge clock);
        reset = 0;
        @(posedge clock);

        // Send two frames of data
        send_frame(0);
        send_frame(1);

        #2000;
        $finish;
    end

    // Task to send one frame of data
    task send_frame;
        input frame_num;
        integer i;
        begin
            for (i = 0; i < N; i = i + 1) begin
                @(posedge clock);
                di_en = 1;
                di_re = i + frame_num * N;
                di_im = N - 1 - i + frame_num * N;
            end
            @(posedge clock);
            di_en = 0;
        end
    endtask

    // Monitor and save output to a file
    integer outfile;
    initial begin
        // File for verification - Declaration must be before use.
        

        $dumpfile("tb_brr_pp.vcd");
        $dumpvars(0, tb_BRR_PP);
        $monitor("Time:%0t\t\tdi_en: %b\tdi_re: %d\tdi_im: %d -> do_en: %b\tdo_re: %d\tdo_im: %d",
                 $time, di_en, di_re, di_im, do_en, do_re, do_im);
        
        outfile = $fopen("output.txt", "w");
        
        forever @(posedge clock) begin
            if (do_en) begin
                $fdisplay(outfile, "%d %d", do_re, do_im);
            end
        end
    end


endmodule

brr_pp_tc/tb_brr_pp.vcd
$date
	Thu Oct 23 17:06:03 2025
$end
$version
	Icarus Verilog
$end
$timescale
	1ps
$end
$scope module tb_BRR_PP $end
$var wire 16 ! do_re [15:0] $end
$var wire 16 " do_im [15:0] $end
$var wire 1 # do_en $end
$var parameter 32 $ BITS $end
$var parameter 32 % CLK_PERIOD $end
$var parameter 32 & N $end
$var parameter 32 ' WIDTH $end
$var reg 1 ( clock $end
$var reg 1 ) di_en $end
$var reg 16 * di_im [15:0] $end
$var reg 16 + di_re [15:0] $end
$var reg 1 , reset $end
$var integer 32 - outfile [31:0] $end
$scope module DUT $end
$var wire 1 ( clock $end
$var wire 1 ) di_en $end
$var wire 16 . di_im [15:0] $end
$var wire 16 / di_re [15:0] $end
$var wire 7 0 rd_addr [6:0] $end
$var wire 1 , reset $end
$var wire 7 1 wr_addr [6:0] $end
$var parameter 32 2 BITS $end
$var parameter 32 3 N $end
$var parameter 32 4 WIDTH $end
$var reg 1 5 buf_sel $end
$var reg 1 # do_en $end
$var reg 16 6 do_im [15:0] $end
$var reg 16 7 do_re [15:0] $end
$var reg 1 8 first_frame $end
$var reg 1 9 rd_active $end
$var reg 7 : rd_cnt [6:0] $end
$var reg 1 ; wr_active $end
$var reg 7 < wr_cnt [6:0] $end
$scope function bit_reverse $end
$var reg 7 = in [6:0] $end
$var integer 32 > i [31:0] $end
$upscope $end
$upscope $end
$scope task send_frame $end
$var reg 1 ? frame_num $end
$var integer 32 @ i [31:0] $end
$upscope $end
$upscope $end
$enddefinitions $end
$comment Show the parameter values. $end
$dumpall
b10000 4
b10000000 3
b111 2
b10000 '
b10000000 &
b1010 %
b111 $
$end
#0
$dumpvars
bx @
x?
b111 >
bx =
bx <
x;
bx :
x9
x8
bx 7
bx 6
x5
bx 1
bx 0
b0 /
b0 .
b10000000000000000000000000000011 -
1,
b0 +
b0 *
0)
0(
x#
bx "
bx !
$end
#5000
b0 1
b111 >
b0 =
18
05
0;
b0 <
0#
09
b0 0
b0 :
1(
#10000
0(
#15000
1(
#20000
0(
#25000
1(
#30000
0(
#35000
1(
#40000
0(
#45000
1(
#50000
0(
#55000
1(
#60000
0(
#65000
1(
#70000
0(
#75000
1(
#80000
0(
#85000
1(
#90000
0(
#95000
1(
#100000
0(
0,
#105000
1(
#110000
0(
#115000
1(
#120000
0(
#125000
1(
#130000
0(
#135000
1(
#140000
0(
#145000
1(
#150000
0(
#155000
1(
#160000
0(
#165000
1(
#170000
0(
#175000
1(
#180000
0(
#185000
1(
#190000
0(
#195000
1(
#200000
0(
1,
#205000
0,
1(
#210000
0(
#215000
b0 @
0?
1(
#220000
0(
#225000
b1000000 1
b111 >
b1 =
b1 <
1;
b1 @
b1111111 *
b1111111 .
1)
1(
#230000
0(
#235000
b100000 1
b111 >
b10 =
b10 <
b10 @
b1111110 *
b1111110 .
b1 +
b1 /
1(
#240000
0(
#245000
b1100000 1
b111 >
b11 =
b11 <
b11 @
b1111101 *
b1111101 .
b10 +
b10 /
1(
#250000
0(
#255000
b10000 1
b111 >
b100 =
b100 <
b100 @
b1111100 *
b1111100 .
b11 +
b11 /
1(
#260000
0(
#265000
b1010000 1
b111 >
b101 =
b101 <
b101 @
b1111011 *
b1111011 .
b100 +
b100 /
1(
#270000
0(
#275000
b110000 1
b111 >
b110 =
b110 <
b110 @
b1111010 *
b1111010 .
b101 +
b101 /
1(
#280000
0(
#285000
b1110000 1
b111 >
b111 =
b111 <
b111 @
b1111001 *
b1111001 .
b110 +
b110 /
1(
#290000
0(
#295000
b1000 1
b111 >
b1000 =
b1000 <
b1000 @
b1111000 *
b1111000 .
b111 +
b111 /
1(
#300000
0(
#305000
b1001000 1
b111 >
b1001 =
b1001 <
b1001 @
b1110111 *
b1110111 .
b1000 +
b1000 /
1(
#310000
0(
#315000
b101000 1
b111 >
b1010 =
b1010 <
b1010 @
b1110110 *
b1110110 .
b1001 +
b1001 /
1(
#320000
0(
#325000
b1101000 1
b111 >
b1011 =
b1011 <
b1011 @
b1110101 *
b1110101 .
b1010 +
b1010 /
1(
#330000
0(
#335000
b11000 1
b111 >
b1100 =
b1100 <
b1100 @
b1110100 *
b1110100 .
b1011 +
b1011 /
1(
#340000
0(
#345000
b1011000 1
b111 >
b1101 =
b1101 <
b1101 @
b1110011 *
b1110011 .
b1100 +
b1100 /
1(
#350000
0(
#355000
b111000 1
b111 >
b1110 =
b1110 <
b1110 @
b1110010 *
b1110010 .
b1101 +
b1101 /
1(
#360000
0(
#365000
b1111000 1
b111 >
b1111 =
b1111 <
b1111 @
b1110001 *
b1110001 .
b1110 +
b1110 /
1(
#370000
0(
#375000
b100 1
b111 >
b10000 =
b10000 <
b10000 @
b1110000 *
b1110000 .
b1111 +
b1111 /
1(
#380000
0(
#385000
b1000100 1
b111 >
b10001 =
b10001 <
b10001 @
b1101111 *
b1101111 .
b10000 +
b10000 /
1(
#390000
0(
#395000
b100100 1
b111 >
b10010 =
b10010 <
b10010 @
b1101110 *
b1101110 .
b10001 +
b10001 /
1(
#400000
0(
#405000
b1100100 1
b111 >
b10011 =
b10011 <
b10011 @
b1101101 *
b1101101 .
b10010 +
b10010 /
1(
#410000
0(
#415000
b10100 1
b111 >
b10100 =
b10100 <
b10100 @
b1101100 *
b1101100 .
b10011 +
b10011 /
1(
#420000
0(
#425000
b1010100 1
b111 >
b10101 =
b10101 <
b10101 @
b1101011 *
b1101011 .
b10100 +
b10100 /
1(
#430000
0(
#435000
b110100 1
b111 >
b10110 =
b10110 <
b10110 @
b1101010 *
b1101010 .
b10101 +
b10101 /
1(
#440000
0(
#445000
b1110100 1
b111 >
b10111 =
b10111 <
b10111 @
b1101001 *
b1101001 .
b10110 +
b10110 /
1(
#450000
0(
#455000
b1100 1
b111 >
b11000 =
b11000 <
b11000 @
b1101000 *
b1101000 .
b10111 +
b10111 /
1(
#460000
0(
#465000
b1001100 1
b111 >
b11001 =
b11001 <
b11001 @
b1100111 *
b1100111 .
b11000 +
b11000 /
1(
#470000
0(
#475000
b101100 1
b111 >
b11010 =
b11010 <
b11010 @
b1100110 *
b1100110 .
b11001 +
b11001 /
1(
#480000
0(
#485000
b1101100 1
b111 >
b11011 =
b11011 <
b11011 @
b1100101 *
b1100101 .
b11010 +
b11010 /
1(
#490000
0(
#495000
b11100 1
b111 >
b11100 =
b11100 <
b11100 @
b1100100 *
b1100100 .
b11011 +
b11011 /
1(
#500000
0(
#505000
b1011100 1
b111 >
b11101 =
b11101 <
b11101 @
b1100011 *
b1100011 .
b11100 +
b11100 /
1(
#510000
0(
#515000
b111100 1
b111 >
b11110 =
b11110 <
b11110 @
b1100010 *
b1100010 .
b11101 +
b11101 /
1(
#520000
0(
#525000
b1111100 1
b111 >
b11111 =
b11111 <
b11111 @
b1100001 *
b1100001 .
b11110 +
b11110 /
1(
#530000
0(
#535000
b10 1
b111 >
b100000 =
b100000 <
b100000 @
b1100000 *
b1100000 .
b11111 +
b11111 /
1(
#540000
0(
#545000
b1000010 1
b111 >
b100001 =
b100001 <
b100001 @
b1011111 *
b1011111 .
b100000 +
b100000 /
1(
#550000
0(
#555000
b100010 1
b111 >
b100010 =
b100010 <
b100010 @
b1011110 *
b1011110 .
b100001 +
b100001 /
1(
#560000
0(
#565000
b1100010 1
b111 >
b100011 =
b100011 <
b100011 @
b1011101 *
b1011101 .
b100010 +
b100010 /
1(
#570000
0(
#575000
b10010 1
b111 >
b100100 =
b100100 <
b100100 @
b1011100 *
b1011100 .
b100011 +
b100011 /
1(
#580000
0(
#585000
b1010010 1
b111 >
b100101 =
b100101 <
b100101 @
b1011011 *
b1011011 .
b100100 +
b100100 /
1(
#590000
0(
#595000
b110010 1
b111 >
b100110 =
b100110 <
b100110 @
b1011010 *
b1011010 .
b100101 +
b100101 /
1(
#600000
0(
#605000
b1110010 1
b111 >
b100111 =
b100111 <
b100111 @
b1011001 *
b1011001 .
b100110 +
b100110 /
1(
#610000
0(
#615000
b1010 1
b111 >
b101000 =
b101000 <
b101000 @
b1011000 *
b1011000 .
b100111 +
b100111 /
1(
#620000
0(
#625000
b1001010 1
b111 >
b101001 =
b101001 <
b101001 @
b1010111 *
b1010111 .
b101000 +
b101000 /
1(
#630000
0(
#635000
b101010 1
b111 >
b101010 =
b101010 <
b101010 @
b1010110 *
b1010110 .
b101001 +
b101001 /
1(
#640000
0(
#645000
b1101010 1
b111 >
b101011 =
b101011 <
b101011 @
b1010101 *
b1010101 .
b101010 +
b101010 /
1(
#650000
0(
#655000
b11010 1
b111 >
b101100 =
b101100 <
b101100 @
b1010100 *
b1010100 .
b101011 +
b101011 /
1(
#660000
0(
#665000
b1011010 1
b111 >
b101101 =
b101101 <
b101101 @
b1010011 *
b1010011 .
b101100 +
b101100 /
1(
#670000
0(
#675000
b111010 1
b111 >
b101110 =
b101110 <
b101110 @
b1010010 *
b1010010 .
b101101 +
b101101 /
1(
#680000
0(
#685000
b1111010 1
b111 >
b101111 =
b101111 <
b101111 @
b1010001 *
b1010001 .
b101110 +
b101110 /
1(
#690000
0(
#695000
b110 1
b111 >
b110000 =
b110000 <
b110000 @
b1010000 *
b1010000 .
b101111 +
b101111 /
1(
#700000
0(
#705000
b1000110 1
b111 >
b110001 =
b110001 <
b110001 @
b1001111 *
b1001111 .
b110000 +
b110000 /
1(
#710000
0(
#715000
b100110 1
b111 >
b110010 =
b110010 <
b110010 @
b1001110 *
b1001110 .
b110001 +
b110001 /
1(
#720000
0(
#725000
b1100110 1
b111 >
b110011 =
b110011 <
b110011 @
b1001101 *
b1001101 .
b110010 +
b110010 /
1(
#730000
0(
#735000
b10110 1
b111 >
b110100 =
b110100 <
b110100 @
b1001100 *
b1001100 .
b110011 +
b110011 /
1(
#740000
0(
#745000
b1010110 1
b111 >
b110101 =
b110101 <
b110101 @
b1001011 *
b1001011 .
b110100 +
b110100 /
1(
#750000
0(
#755000
b110110 1
b111 >
b110110 =
b110110 <
b110110 @
b1001010 *
b1001010 .
b110101 +
b110101 /
1(
#760000
0(
#765000
b1110110 1
b111 >
b110111 =
b110111 <
b110111 @
b1001001 *
b1001001 .
b110110 +
b110110 /
1(
#770000
0(
#775000
b1110 1
b111 >
b111000 =
b111000 <
b111000 @
b1001000 *
b1001000 .
b110111 +
b110111 /
1(
#780000
0(
#785000
b1001110 1
b111 >
b111001 =
b111001 <
b111001 @
b1000111 *
b1000111 .
b111000 +
b111000 /
1(
#790000
0(
#795000
b101110 1
b111 >
b111010 =
b111010 <
b111010 @
b1000110 *
b1000110 .
b111001 +
b111001 /
1(
#800000
0(
#805000
b1101110 1
b111 >
b111011 =
b111011 <
b111011 @
b1000101 *
b1000101 .
b111010 +
b111010 /
1(
#810000
0(
#815000
b11110 1
b111 >
b111100 =
b111100 <
b111100 @
b1000100 *
b1000100 .
b111011 +
b111011 /
1(
#820000
0(
#825000
b1011110 1
b111 >
b111101 =
b111101 <
b111101 @
b1000011 *
b1000011 .
b111100 +
b111100 /
1(
#830000
0(
#835000
b111110 1
b111 >
b111110 =
b111110 <
b111110 @
b1000010 *
b1000010 .
b111101 +
b111101 /
1(
#840000
0(
#845000
b1111110 1
b111 >
b111111 =
b111111 <
b111111 @
b1000001 *
b1000001 .
b111110 +
b111110 /
1(
#850000
0(
#855000
b1 1
b111 >
b1000000 =
b1000000 <
b1000000 @
b1000000 *
b1000000 .
b111111 +
b111111 /
1(
#860000
0(
#865000
b1000001 1
b111 >
b1000001 =
b1000001 <
b1000001 @
b111111 *
b111111 .
b1000000 +
b1000000 /
1(
#870000
0(
#875000
b100001 1
b111 >
b1000010 =
b1000010 <
b1000010 @
b111110 *
b111110 .
b1000001 +
b1000001 /
1(
#880000
0(
#885000
b1100001 1
b111 >
b1000011 =
b1000011 <
b1000011 @
b111101 *
b111101 .
b1000010 +
b1000010 /
1(
#890000
0(
#895000
b10001 1
b111 >
b1000100 =
b1000100 <
b1000100 @
b111100 *
b111100 .
b1000011 +
b1000011 /
1(
#900000
0(
#905000
b1010001 1
b111 >
b1000101 =
b1000101 <
b1000101 @
b111011 *
b111011 .
b1000100 +
b1000100 /
1(
#910000
0(
#915000
b110001 1
b111 >
b1000110 =
b1000110 <
b1000110 @
b111010 *
b111010 .
b1000101 +
b1000101 /
1(
#920000
0(
#925000
b1110001 1
b111 >
b1000111 =
b1000111 <
b1000111 @
b111001 *
b111001 .
b1000110 +
b1000110 /
1(
#930000
0(
#935000
b1001 1
b111 >
b1001000 =
b1001000 <
b1001000 @
b111000 *
b111000 .
b1000111 +
b1000111 /
1(
#940000
0(
#945000
b1001001 1
b111 >
b1001001 =
b1001001 <
b1001001 @
b110111 *
b110111 .
b1001000 +
b1001000 /
1(
#950000
0(
#955000
b101001 1
b111 >
b1001010 =
b1001010 <
b1001010 @
b110110 *
b110110 .
b1001001 +
b1001001 /
1(
#960000
0(
#965000
b1101001 1
b111 >
b1001011 =
b1001011 <
b1001011 @
b110101 *
b110101 .
b1001010 +
b1001010 /
1(
#970000
0(
#975000
b11001 1
b111 >
b1001100 =
b1001100 <
b1001100 @
b110100 *
b110100 .
b1001011 +
b1001011 /
1(
#980000
0(
#985000
b1011001 1
b111 >
b1001101 =
b1001101 <
b1001101 @
b110011 *
b110011 .
b1001100 +
b1001100 /
1(
#990000
0(
#995000
b111001 1
b111 >
b1001110 =
b1001110 <
b1001110 @
b110010 *
b110010 .
b1001101 +
b1001101 /
1(
#1000000
0(
#1005000
b1111001 1
b111 >
b1001111 =
b1001111 <
b1001111 @
b110001 *
b110001 .
b1001110 +
b1001110 /
1(
#1010000
0(
#1015000
b101 1
b111 >
b1010000 =
b1010000 <
b1010000 @
b110000 *
b110000 .
b1001111 +
b1001111 /
1(
#1020000
0(
#1025000
b1000101 1
b111 >
b1010001 =
b1010001 <
b1010001 @
b101111 *
b101111 .
b1010000 +
b1010000 /
1(
#1030000
0(
#1035000
b100101 1
b111 >
b1010010 =
b1010010 <
b1010010 @
b101110 *
b101110 .
b1010001 +
b1010001 /
1(
#1040000
0(
#1045000
b1100101 1
b111 >
b1010011 =
b1010011 <
b1010011 @
b101101 *
b101101 .
b1010010 +
b1010010 /
1(
#1050000
0(
#1055000
b10101 1
b111 >
b1010100 =
b1010100 <
b1010100 @
b101100 *
b101100 .
b1010011 +
b1010011 /
1(
#1060000
0(
#1065000
b1010101 1
b111 >
b1010101 =
b1010101 <
b1010101 @
b101011 *
b101011 .
b1010100 +
b1010100 /
1(
#1070000
0(
#1075000
b110101 1
b111 >
b1010110 =
b1010110 <
b1010110 @
b101010 *
b101010 .
b1010101 +
b1010101 /
1(
#1080000
0(
#1085000
b1110101 1
b111 >
b1010111 =
b1010111 <
b1010111 @
b101001 *
b101001 .
b1010110 +
b1010110 /
1(
#1090000
0(
#1095000
b1101 1
b111 >
b1011000 =
b1011000 <
b1011000 @
b101000 *
b101000 .
b1010111 +
b1010111 /
1(
#1100000
0(
#1105000
b1001101 1
b111 >
b1011001 =
b1011001 <
b1011001 @
b100111 *
b100111 .
b1011000 +
b1011000 /
1(
#1110000
0(
#1115000
b101101 1
b111 >
b1011010 =
b1011010 <
b1011010 @
b100110 *
b100110 .
b1011001 +
b1011001 /
1(
#1120000
0(
#1125000
b1101101 1
b111 >
b1011011 =
b1011011 <
b1011011 @
b100101 *
b100101 .
b1011010 +
b1011010 /
1(
#1130000
0(
#1135000
b11101 1
b111 >
b1011100 =
b1011100 <
b1011100 @
b100100 *
b100100 .
b1011011 +
b1011011 /
1(
#1140000
0(
#1145000
b1011101 1
b111 >
b1011101 =
b1011101 <
b1011101 @
b100011 *
b100011 .
b1011100 +
b1011100 /
1(
#1150000
0(
#1155000
b111101 1
b111 >
b1011110 =
b1011110 <
b1011110 @
b100010 *
b100010 .
b1011101 +
b1011101 /
1(
#1160000
0(
#1165000
b1111101 1
b111 >
b1011111 =
b1011111 <
b1011111 @
b100001 *
b100001 .
b1011110 +
b1011110 /
1(
#1170000
0(
#1175000
b11 1
b111 >
b1100000 =
b1100000 <
b1100000 @
b100000 *
b100000 .
b1011111 +
b1011111 /
1(
#1180000
0(
#1185000
b1000011 1
b111 >
b1100001 =
b1100001 <
b1100001 @
b11111 *
b11111 .
b1100000 +
b1100000 /
1(
#1190000
0(
#1195000
b100011 1
b111 >
b1100010 =
b1100010 <
b1100010 @
b11110 *
b11110 .
b1100001 +
b1100001 /
1(
#1200000
0(
#1205000
b1100011 1
b111 >
b1100011 =
b1100011 <
b1100011 @
b11101 *
b11101 .
b1100010 +
b1100010 /
1(
#1210000
0(
#1215000
b10011 1
b111 >
b1100100 =
b1100100 <
b1100100 @
b11100 *
b11100 .
b1100011 +
b1100011 /
1(
#1220000
0(
#1225000
b1010011 1
b111 >
b1100101 =
b1100101 <
b1100101 @
b11011 *
b11011 .
b1100100 +
b1100100 /
1(
#1230000
0(
#1235000
b110011 1
b111 >
b1100110 =
b1100110 <
b1100110 @
b11010 *
b11010 .
b1100101 +
b1100101 /
1(
#1240000
0(
#1245000
b1110011 1
b111 >
b1100111 =
b1100111 <
b1100111 @
b11001 *
b11001 .
b1100110 +
b1100110 /
1(
#1250000
0(
#1255000
b1011 1
b111 >
b1101000 =
b1101000 <
b1101000 @
b11000 *
b11000 .
b1100111 +
b1100111 /
1(
#1260000
0(
#1265000
b1001011 1
b111 >
b1101001 =
b1101001 <
b1101001 @
b10111 *
b10111 .
b1101000 +
b1101000 /
1(
#1270000
0(
#1275000
b101011 1
b111 >
b1101010 =
b1101010 <
b1101010 @
b10110 *
b10110 .
b1101001 +
b1101001 /
1(
#1280000
0(
#1285000
b1101011 1
b111 >
b1101011 =
b1101011 <
b1101011 @
b10101 *
b10101 .
b1101010 +
b1101010 /
1(
#1290000
0(
#1295000
b11011 1
b111 >
b1101100 =
b1101100 <
b1101100 @
b10100 *
b10100 .
b1101011 +
b1101011 /
1(
#1300000
0(
#1305000
b1011011 1
b111 >
b1101101 =
b1101101 <
b1101101 @
b10011 *
b10011 .
b1101100 +
b1101100 /
1(
#1310000
0(
#1315000
b111011 1
b111 >
b1101110 =
b1101110 <
b1101110 @
b10010 *
b10010 .
b1101101 +
b1101101 /
1(
#1320000
0(
#1325000
b1111011 1
b111 >
b1101111 =
b1101111 <
b1101111 @
b10001 *
b10001 .
b1101110 +
b1101110 /
1(
#1330000
0(
#1335000
b111 1
b111 >
b1110000 =
b1110000 <
b1110000 @
b10000 *
b10000 .
b1101111 +
b1101111 /
1(
#1340000
0(
#1345000
b1000111 1
b111 >
b1110001 =
b1110001 <
b1110001 @
b1111 *
b1111 .
b1110000 +
b1110000 /
1(
#1350000
0(
#1355000
b100111 1
b111 >
b1110010 =
b1110010 <
b1110010 @
b1110 *
b1110 .
b1110001 +
b1110001 /
1(
#1360000
0(
#1365000
b1100111 1
b111 >
b1110011 =
b1110011 <
b1110011 @
b1101 *
b1101 .
b1110010 +
b1110010 /
1(
#1370000
0(
#1375000
b10111 1
b111 >
b1110100 =
b1110100 <
b1110100 @
b1100 *
b1100 .
b1110011 +
b1110011 /
1(
#1380000
0(
#1385000
b1010111 1
b111 >
b1110101 =
b1110101 <
b1110101 @
b1011 *
b1011 .
b1110100 +
b1110100 /
1(
#1390000
0(
#1395000
b110111 1
b111 >
b1110110 =
b1110110 <
b1110110 @
b1010 *
b1010 .
b1110101 +
b1110101 /
1(
#1400000
0(
#1405000
b1110111 1
b111 >
b1110111 =
b1110111 <
b1110111 @
b1001 *
b1001 .
b1110110 +
b1110110 /
1(
#1410000
0(
#1415000
b1111 1
b111 >
b1111000 =
b1111000 <
b1111000 @
b1000 *
b1000 .
b1110111 +
b1110111 /
1(
#1420000
0(
#1425000
b1001111 1
b111 >
b1111001 =
b1111001 <
b1111001 @
b111 *
b111 .
b1111000 +
b1111000 /
1(
#1430000
0(
#1435000
b101111 1
b111 >
b1111010 =
b1111010 <
b1111010 @
b110 *
b110 .
b1111001 +
b1111001 /
1(
#1440000
0(
#1445000
b1101111 1
b111 >
b1111011 =
b1111011 <
b1111011 @
b101 *
b101 .
b1111010 +
b1111010 /
1(
#1450000
0(
#1455000
b11111 1
b111 >
b1111100 =
b1111100 <
b1111100 @
b100 *
b100 .
b1111011 +
b1111011 /
1(
#1460000
0(
#1465000
b1011111 1
b111 >
b1111101 =
b1111101 <
b1111101 @
b11 *
b11 .
b1111100 +
b1111100 /
1(
#1470000
0(
#1475000
b111111 1
b111 >
b1111110 =
b1111110 <
b1111110 @
b10 *
b10 .
b1111101 +
b1111101 /
1(
#1480000
0(
#1485000
b1111111 1
b111 >
b1111111 =
b1111111 <
b1111111 @
b1 *
b1 .
b1111110 +
b1111110 /
1(
#1490000
0(
#1495000
b0 1
b111 >
b0 =
19
0;
08
15
b0 <
b10000000 @
b0 *
b0 .
b1111111 +
b1111111 /
1(
#1500000
0(
#1505000
b1 0
b1 :
1#
b1111111 "
b1111111 6
b0 !
b0 7
b0 @
1?
0)
1(
#1510000
0(
#1515000
b1000000 1
b111 >
b1 =
b10 0
b10 :
b111111 "
b111111 6
b1000000 !
b1000000 7
b1 <
1;
b1 @
b11111111 *
b11111111 .
b10000000 +
b10000000 /
1)
1(
#1520000
0(
#1525000
b100000 1
b111 >
b10 =
b10 <
b11 0
b11 :
b1011111 "
b1011111 6
b100000 !
b100000 7
b10 @
b11111110 *
b11111110 .
b10000001 +
b10000001 /
1(
#1530000
0(
#1535000
b1100000 1
b111 >
b11 =
b100 0
b100 :
b11111 "
b11111 6
b1100000 !
b1100000 7
b11 <
b11 @
b11111101 *
b11111101 .
b10000010 +
b10000010 /
1(
#1540000
0(
#1545000
b10000 1
b111 >
b100 =
b100 <
b101 0
b101 :
b1101111 "
b1101111 6
b10000 !
b10000 7
b100 @
b11111100 *
b11111100 .
b10000011 +
b10000011 /
1(
#1550000
0(
#1555000
b1010000 1
b111 >
b101 =
b110 0
b110 :
b101111 "
b101111 6
b1010000 !
b1010000 7
b101 <
b101 @
b11111011 *
b11111011 .
b10000100 +
b10000100 /
1(
#1560000
0(
#1565000
b110000 1
b111 >
b110 =
b110 <
b111 0
b111 :
b1001111 "
b1001111 6
b110000 !
b110000 7
b110 @
b11111010 *
b11111010 .
b10000101 +
b10000101 /
1(
#1570000
0(
#1575000
b1110000 1
b111 >
b111 =
b1000 0
b1000 :
b1111 "
b1111 6
b1110000 !
b1110000 7
b111 <
b111 @
b11111001 *
b11111001 .
b10000110 +
b10000110 /
1(
#1580000
0(
