buffer.v
module buffer #(
    parameter DATA_WIDTH = 16,
    parameter DEPTH = 128,
    parameter ADDR_WIDTH = $clog2(DEPTH) // Should be ceil(log2(DEPTH))
) (
    input clk,
    input rst,
    input reg_write,
    input [ADDR_WIDTH-1:0] read_addr,
    input [ADDR_WIDTH-1:0] write_addr,
    input [DATA_WIDTH-1:0] write_data,
    output [DATA_WIDTH-1:0] read_data
);

    // Register array declaration
    reg [DATA_WIDTH-1:0] reg_array [DEPTH-1:0];

    // Synchronous write operation
    integer i;
    always @(posedge clk or posedge rst) begin
        if (rst) begin
            // Optional: Reset all registers to zero
            for (i=0; i < DEPTH; i=i+1) begin
                reg_array[i] <= 0;
            end
        end else if (reg_write) begin
            reg_array[write_addr] <= write_data;
        end else begin
            for (i=0; i < DEPTH; i=i+1) begin
                reg_array[i] <= reg_array[i];
            end
        end
    end

    // Asynchronous read operations
    assign read_data = reg_array[read_addr];

endmodule

BitRevReorder.v
module BRR_PP #(
    parameter DATA_WIDTH = 8,
    parameter ADDR_WIDTH = 8
) (
    // Inputs
    input clk,
    input rst,
    input wr_en,
    input rd_en,
    input [DATA_WIDTH-1:0] data_in,

    // Outputs
    output [DATA_WIDTH-1:0] data_out,
    output reg buffer_full,
    output reg buffer_empty
);

    localparam DEPTH = 1 << ADDR_WIDTH;


    // Pointers for writing and reading
    reg [ADDR_WIDTH:0] write_counter;
    reg [ADDR_WIDTH:0] read_counter;

    // Bank selection signals
    reg wr_bank; // 0 for mem_a, 1 for mem_b
    reg rd_bank; // 0 for mem_a, 1 for mem_b

    // Write and read addresses
    wire [ADDR_WIDTH-1:0] wr_addr;
    wire [ADDR_WIDTH-1:0] rd_addr;
    wire [DATA_WIDTH-1:0] data_out_a;
    wire [DATA_WIDTH-1:0] data_out_b;


    // Function to reverse the bits of a vector
    function [ADDR_WIDTH-1:0] bit_reverse;
        input [ADDR_WIDTH-1:0] in;
        integer i;
        begin
            // Build the reversed-bit vector bit-by-bit
            for (i = 0; i < ADDR_WIDTH; i = i + 1)
                bit_reverse[i] = in[ADDR_WIDTH-1-i];
        end
    endfunction

    // Generate write address by bit-reversing the write_counter
    assign wr_addr = bit_reverse(write_counter);

    // Read address is the natural order read_counter
    assign rd_addr = read_counter;


    // Counters and bank switching logic
    always @(posedge clk or posedge rst) begin
        if (rst) begin
            write_counter <= 0;
            read_counter  <= 0;
            wr_bank       <= 0;
            rd_bank       <= 1;
            buffer_full   <= 0;
            buffer_empty  <= 1;
        end else begin
            // Write counter logic and bank switching

            if (wr_en) begin
                if (write_counter == DEPTH) begin
                    write_counter <= 1;
                    wr_bank       <= ~wr_bank; // Switch write bank
                    rd_bank       <= ~rd_bank; // force read bank switch: sync with write
                    buffer_full   <= 1;       // Signal that a buffer is full
                end else begin
                    write_counter <= write_counter + 1;
                    buffer_full   <= 0;
                end
            end

            // Read counter logic
            if (rd_en) begin
                if (read_counter == DEPTH) begin
                    read_counter <= 1;
                    buffer_empty <= 1;     
                    rd_bank      <= ~rd_bank; // Signal that a buffer is empty
                end else begin
                    read_counter <= read_counter + 1;
                    buffer_empty <= 0;
                end
            end

        end
    end

    // Output multiplexer
    assign data_out = (rd_bank == 0) ? data_out_a : data_out_b;

    buffer #(
        .DATA_WIDTH(DATA_WIDTH),
        .DEPTH(DEPTH),
        .ADDR_WIDTH(ADDR_WIDTH)
    ) buffer_a (
        .clk(clk),
        .rst(rst),
        .reg_write(wr_en && ~wr_bank),
        .read_addr(rd_addr),
        .write_addr(wr_addr),
        .write_data(data_in),
        .read_data(data_out_a)
    );

    buffer #(
        .DATA_WIDTH(DATA_WIDTH),
        .DEPTH(DEPTH),
        .ADDR_WIDTH(ADDR_WIDTH)
    ) buffer_b (
        .clk(clk),
        .rst(rst),
        .reg_write(wr_en && wr_bank),
        .read_addr(rd_addr),
        .write_addr(wr_addr),
        .write_data(data_in),
        .read_data(data_out_b)
    );

    // integer monitor_file;
    initial begin
       $monitor("Time: %0t\twr_en: %0d\trd_en: %0d\twr_bank: %0d\trd_bank: %0d\tWrite Addr: %0d\tData In: %0d\t Read Addr: %0d\tData Out: %0d", $time, wr_en, rd_en, wr_bank, rd_bank, wr_addr, data_in, rd_addr, data_out);
    end
    // forever begin
    //     if (rd_en) begin
    //         
    //     end
    // end
endmodule

brr_pp_tc/tb_BRR_PP.v
`timescale 1ns / 1ps

module tb_BRR_PP;

    // Parameters matching the DUT and verification script
    localparam ADDR_WIDTH = 7;
    localparam DATA_WIDTH = 16;
    localparam DEPTH      = 1 << ADDR_WIDTH; // Should be 128
    localparam CLK_PERIOD = 10;

    // Testbench signals
    reg                      clk;
    reg                      rst;
    reg                      wr_en;
    reg                      rd_en;
    reg  [DATA_WIDTH-1:0]    data_in;

    wire [DATA_WIDTH-1:0]    data_out;
    wire                     buffer_full;
    wire                     buffer_empty;

    // Instantiate the DUT (Device Under Test)
    BRR_PP #(
        .DATA_WIDTH(DATA_WIDTH),
        .ADDR_WIDTH(ADDR_WIDTH)
    ) DUT (
        .clk(clk),
        .rst(rst),
        .wr_en(wr_en),
        .rd_en(rd_en),
        .data_in(data_in),
        .data_out(data_out),
        .buffer_full(buffer_full),
        .buffer_empty(buffer_empty)
    );

    // Clock generation
    initial begin
        clk = 0;
        forever #(CLK_PERIOD/2) clk = ~clk;
    end

    // Main stimulus block
    initial begin
        // 1. Initialize and Reset
        $display("Starting testbench...");
        rst = 1;
        wr_en = 0;
        rd_en = 0;
        data_in = 0;
        #(CLK_PERIOD * 5);
        rst = 0;
        #(CLK_PERIOD);

        // Wait for reset to de-assert
        $display("Reset released. Starting data transmission.");

        // 2. Write the first frame of data (to Buffer A)
        $display("Writing Frame 0...");
        write_frame(0);

        // After writing, the 'other' buffer is now ready for reading.
        // We must wait one cycle for the read address to be registered.
        @(posedge clk);

        // 3. Simultaneously READ Frame 0 (from Buffer A) and WRITE Frame 1 (to Buffer B)
        $display("Concurrently Reading Frame 0 and Writing Frame 1...");
        fork
            read_frame();
            write_frame(1);
        join
        
        // Wait one cycle for read address to be registered.
        @(posedge clk);

        // 4. Read the second frame of data (from Buffer B)
        $display("Reading Frame 1...");
        read_frame();

        // End of test
        #(CLK_PERIOD * 10);
        $display("Test finished.");
        $finish;
    end

    function [ADDR_WIDTH-1:0] bit_reverse;
        input [ADDR_WIDTH-1:0] in;
        integer i;
        begin
            for (i = 0; i < ADDR_WIDTH; i = i + 1)
                bit_reverse[i] = in[ADDR_WIDTH-1-i];
        end
    endfunction

    // Task to write one frame of data
    task write_frame;

        
        input integer frame_num;
        integer i;
        begin
            wr_en = 1;
            for (i = 0; i < DEPTH; i = i + 1) begin
                
                // Send sequential data values
                data_in = bit_reverse(i) + frame_num * DEPTH + 1;
                @(posedge clk);
            end
            @(posedge clk);
            wr_en = 0;
        end
    endtask

    // Task to read one frame of data
    task read_frame;
        integer i;
        begin
            for (i = 0; i < DEPTH; i = i + 1) begin
                rd_en = 1;
                @(posedge clk);
            end
            @(posedge clk);
            rd_en = 0;
        end
    endtask

    // Monitor: Save output data to a file for verification
    integer outfile;
    initial begin
        // Setup simulation dump
        $dumpfile("tb_brr_pp.vcd");
        $dumpvars(0, tb_BRR_PP);

        // Open file for output
        outfile = $fopen("output.txt", "w");
        
        // Forever loop to monitor the output
        forever @(posedge clk) begin
            // Data is valid on the cycle that rd_en is high
            if (rd_en) begin
                #CLK_PERIOD; // Wait for data_out to stabilize
                $fdisplay(outfile, "%d %d", data_out, 0);
            end
        end
    end

endmodule

brr_pp_tc/tb_brr_pp.vcd
$date
	Sat Oct 25 12:42:29 2025
$end
$version
	Icarus Verilog
$end
$timescale
	1ps
$end
$scope module tb_BRR_PP $end
$var wire 16 ! data_out [15:0] $end
$var wire 1 " buffer_full $end
$var wire 1 # buffer_empty $end
$var parameter 32 $ ADDR_WIDTH $end
$var parameter 32 % CLK_PERIOD $end
$var parameter 32 & DATA_WIDTH $end
$var parameter 39 ' DEPTH $end
$var reg 1 ( clk $end
$var reg 16 ) data_in [15:0] $end
$var reg 1 * rd_en $end
$var reg 1 + rst $end
$var reg 1 , wr_en $end
$var integer 32 - outfile [31:0] $end
$scope function bit_reverse $end
$var reg 7 . in [6:0] $end
$var integer 32 / i [31:0] $end
$upscope $end
$scope module DUT $end
$var wire 1 ( clk $end
$var wire 16 0 data_in [15:0] $end
$var wire 1 * rd_en $end
$var wire 1 + rst $end
$var wire 1 , wr_en $end
$var wire 7 1 wr_addr [6:0] $end
$var wire 7 2 rd_addr [6:0] $end
$var wire 16 3 data_out_b [15:0] $end
$var wire 16 4 data_out_a [15:0] $end
$var wire 16 5 data_out [15:0] $end
$var parameter 32 6 ADDR_WIDTH $end
$var parameter 32 7 DATA_WIDTH $end
$var parameter 39 8 DEPTH $end
$var reg 1 # buffer_empty $end
$var reg 1 " buffer_full $end
$var reg 1 9 rd_bank $end
$var reg 8 : read_counter [7:0] $end
$var reg 1 ; wr_bank $end
$var reg 8 < write_counter [7:0] $end
$scope function bit_reverse $end
$var reg 7 = in [6:0] $end
$var integer 32 > i [31:0] $end
$upscope $end
$scope module buffer_a $end
$var wire 1 ( clk $end
$var wire 7 ? read_addr [6:0] $end
$var wire 16 @ read_data [15:0] $end
$var wire 1 A reg_write $end
$var wire 1 + rst $end
$var wire 7 B write_addr [6:0] $end
$var wire 16 C write_data [15:0] $end
$var parameter 32 D ADDR_WIDTH $end
$var parameter 32 E DATA_WIDTH $end
$var parameter 39 F DEPTH $end
$var integer 32 G i [31:0] $end
$upscope $end
$scope module buffer_b $end
$var wire 1 ( clk $end
$var wire 7 H read_addr [6:0] $end
$var wire 16 I read_data [15:0] $end
$var wire 1 J reg_write $end
$var wire 1 + rst $end
$var wire 7 K write_addr [6:0] $end
$var wire 16 L write_data [15:0] $end
$var parameter 32 M ADDR_WIDTH $end
$var parameter 32 N DATA_WIDTH $end
$var parameter 39 O DEPTH $end
$var integer 32 P i [31:0] $end
$upscope $end
$upscope $end
$scope task read_frame $end
$var integer 32 Q i [31:0] $end
$upscope $end
$scope task write_frame $end
$var integer 32 R frame_num [31:0] $end
$var integer 32 S i [31:0] $end
$upscope $end
$upscope $end
$enddefinitions $end
$comment Show the parameter values. $end
$dumpall
b10000000 O
b10000 N
b111 M
b10000000 F
b10000 E
b111 D
b10000000 8
b10000 7
b111 6
b10000000 '
b10000 &
b1010 %
b111 $
$end
#0
$dumpvars
bx S
bx R
bx Q
b10000000 P
b0 L
b0 K
0J
b0 I
b0 H
b10000000 G
b0 C
b0 B
0A
b0 @
b0 ?
b111 >
b0 =
b0 <
0;
b0 :
19
b0 5
b0 4
b0 3
b0 2
b0 1
b0 0
bx /
bx .
b10000000000000000000000000000011 -
0,
1+
0*
b0 )
0(
1#
0"
b0 !
$end
#5000
b10000000 P
b10000000 G
1(
#10000
0(
#15000
b10000000 G
b10000000 P
1(
#20000
0(
#25000
b10000000 P
b10000000 G
1(
#30000
0(
#35000
b10000000 G
b10000000 P
1(
#40000
0(
#45000
b10000000 P
b10000000 G
1(
#50000
0(
0+
#55000
b10000000 G
b10000000 P
1(
#60000
1A
0(
b1 )
b1 0
b1 C
b1 L
b111 /
b0 .
b0 S
1,
b0 R
#65000
b1000000 1
b1000000 B
b1000000 K
b111 >
b1 =
b1 <
b1000001 4
b1000001 @
b10000000 P
b1000001 )
b1000001 0
b1000001 C
b1000001 L
b111 /
b1 .
b1 S
1(
#70000
0(
#75000
b100000 1
b100000 B
b100000 K
b111 >
b10 =
b10 <
b10000000 P
b100001 )
b100001 0
b100001 C
b100001 L
b111 /
b10 .
b10 S
1(
#80000
0(
#85000
b1100000 1
b1100000 B
b1100000 K
b111 >
b11 =
b11 <
b10000000 P
b1100001 )
b1100001 0
b1100001 C
b1100001 L
b111 /
b11 .
b11 S
1(
#90000
0(
#95000
b10000 1
b10000 B
b10000 K
b111 >
b100 =
b100 <
b10000000 P
b10001 )
b10001 0
b10001 C
b10001 L
b111 /
b100 .
b100 S
1(
#100000
0(
#105000
b1010000 1
b1010000 B
b1010000 K
b111 >
b101 =
b101 <
b10000000 P
b1010001 )
b1010001 0
b1010001 C
b1010001 L
b111 /
b101 .
b101 S
1(
#110000
0(
#115000
b110000 1
b110000 B
b110000 K
b111 >
b110 =
b110 <
b10000000 P
b110001 )
b110001 0
b110001 C
b110001 L
b111 /
b110 .
b110 S
1(
#120000
0(
#125000
b1110000 1
b1110000 B
b1110000 K
b111 >
b111 =
b111 <
b10000000 P
b1110001 )
b1110001 0
b1110001 C
b1110001 L
b111 /
b111 .
b111 S
1(
#130000
0(
#135000
b1000 1
b1000 B
b1000 K
b111 >
b1000 =
b1000 <
b10000000 P
b1001 )
b1001 0
b1001 C
b1001 L
b111 /
b1000 .
b1000 S
1(
#140000
0(
#145000
b1001000 1
b1001000 B
b1001000 K
b111 >
b1001 =
b1001 <
b10000000 P
b1001001 )
b1001001 0
b1001001 C
b1001001 L
b111 /
b1001 .
b1001 S
1(
#150000
0(
#155000
b101000 1
b101000 B
b101000 K
b111 >
b1010 =
b1010 <
b10000000 P
b101001 )
b101001 0
b101001 C
b101001 L
b111 /
b1010 .
b1010 S
1(
#160000
0(
#165000
b1101000 1
b1101000 B
b1101000 K
b111 >
b1011 =
b1011 <
b10000000 P
b1101001 )
b1101001 0
b1101001 C
b1101001 L
b111 /
b1011 .
b1011 S
1(
#170000
0(
#175000
b11000 1
b11000 B
b11000 K
b111 >
b1100 =
b1100 <
b10000000 P
b11001 )
b11001 0
b11001 C
b11001 L
b111 /
b1100 .
b1100 S
1(
#180000
0(
#185000
b1011000 1
b1011000 B
b1011000 K
b111 >
b1101 =
b1101 <
b10000000 P
b1011001 )
b1011001 0
b1011001 C
b1011001 L
b111 /
b1101 .
b1101 S
1(
#190000
0(
#195000
b111000 1
b111000 B
b111000 K
b111 >
b1110 =
b1110 <
b10000000 P
b111001 )
b111001 0
b111001 C
b111001 L
b111 /
b1110 .
b1110 S
1(
#200000
0(
#205000
b1111000 1
b1111000 B
b1111000 K
b111 >
b1111 =
b1111 <
b10000000 P
b1111001 )
b1111001 0
b1111001 C
b1111001 L
b111 /
b1111 .
b1111 S
1(
#210000
0(
#215000
b100 1
b100 B
b100 K
b111 >
b10000 =
b10000 <
b10000000 P
b101 )
b101 0
b101 C
b101 L
b111 /
b10000 .
b10000 S
1(
#220000
0(
#225000
b1000100 1
b1000100 B
b1000100 K
b111 >
b10001 =
b10001 <
b10000000 P
b1000101 )
b1000101 0
b1000101 C
b1000101 L
b111 /
b10001 .
b10001 S
1(
#230000
0(
#235000
b100100 1
b100100 B
b100100 K
b111 >
b10010 =
b10010 <
b10000000 P
b100101 )
b100101 0
b100101 C
b100101 L
b111 /
b10010 .
b10010 S
1(
#240000
0(
#245000
b1100100 1
b1100100 B
b1100100 K
b111 >
b10011 =
b10011 <
b10000000 P
b1100101 )
b1100101 0
b1100101 C
b1100101 L
b111 /
b10011 .
b10011 S
1(
#250000
0(
#255000
b10100 1
b10100 B
b10100 K
b111 >
b10100 =
b10100 <
b10000000 P
b10101 )
b10101 0
b10101 C
b10101 L
b111 /
b10100 .
b10100 S
1(
#260000
0(
#265000
b1010100 1
b1010100 B
b1010100 K
b111 >
b10101 =
b10101 <
b10000000 P
b1010101 )
b1010101 0
b1010101 C
b1010101 L
b111 /
b10101 .
b10101 S
1(
#270000
0(
#275000
b110100 1
b110100 B
b110100 K
b111 >
b10110 =
b10110 <
b10000000 P
b110101 )
b110101 0
b110101 C
b110101 L
b111 /
b10110 .
b10110 S
1(
#280000
0(
#285000
b1110100 1
b1110100 B
b1110100 K
b111 >
b10111 =
b10111 <
b10000000 P
b1110101 )
b1110101 0
b1110101 C
b1110101 L
b111 /
b10111 .
b10111 S
1(
#290000
0(
#295000
b1100 1
b1100 B
b1100 K
b111 >
b11000 =
b11000 <
b10000000 P
b1101 )
b1101 0
b1101 C
b1101 L
b111 /
b11000 .
b11000 S
1(
#300000
0(
#305000
b1001100 1
b1001100 B
b1001100 K
b111 >
b11001 =
b11001 <
b10000000 P
b1001101 )
b1001101 0
b1001101 C
b1001101 L
b111 /
b11001 .
b11001 S
1(
#310000
0(
#315000
b101100 1
b101100 B
b101100 K
b111 >
b11010 =
b11010 <
b10000000 P
b101101 )
b101101 0
b101101 C
b101101 L
b111 /
b11010 .
b11010 S
1(
#320000
0(
#325000
b1101100 1
b1101100 B
b1101100 K
b111 >
b11011 =
b11011 <
b10000000 P
b1101101 )
b1101101 0
b1101101 C
b1101101 L
b111 /
b11011 .
b11011 S
1(
#330000
0(
#335000
b11100 1
b11100 B
b11100 K
b111 >
b11100 =
b11100 <
b10000000 P
b11101 )
b11101 0
b11101 C
b11101 L
b111 /
b11100 .
b11100 S
1(
#340000
0(
#345000
b1011100 1
b1011100 B
b1011100 K
b111 >
b11101 =
b11101 <
b10000000 P
b1011101 )
b1011101 0
b1011101 C
b1011101 L
b111 /
b11101 .
b11101 S
1(
#350000
0(
#355000
b111100 1
b111100 B
b111100 K
b111 >
b11110 =
b11110 <
b10000000 P
b111101 )
b111101 0
b111101 C
b111101 L
b111 /
b11110 .
b11110 S
1(
#360000
0(
#365000
b1111100 1
b1111100 B
b1111100 K
b111 >
b11111 =
b11111 <
b10000000 P
b1111101 )
b1111101 0
b1111101 C
b1111101 L
b111 /
b11111 .
b11111 S
1(
#370000
0(
#375000
b10 1
b10 B
b10 K
b111 >
b100000 =
b100000 <
b10000000 P
b11 )
b11 0
b11 C
b11 L
b111 /
b100000 .
b100000 S
1(
#380000
0(
#385000
b1000010 1
b1000010 B
b1000010 K
b111 >
b100001 =
b100001 <
b10000000 P
b1000011 )
b1000011 0
b1000011 C
b1000011 L
b111 /
b100001 .
b100001 S
1(
#390000
0(
#395000
b100010 1
b100010 B
b100010 K
b111 >
b100010 =
b100010 <
b10000000 P
b100011 )
b100011 0
b100011 C
b100011 L
b111 /
b100010 .
b100010 S
1(
#400000
0(
#405000
b1100010 1
b1100010 B
b1100010 K
b111 >
b100011 =
b100011 <
b10000000 P
b1100011 )
b1100011 0
b1100011 C
b1100011 L
b111 /
b100011 .
b100011 S
1(
#410000
0(
#415000
b10010 1
b10010 B
b10010 K
b111 >
b100100 =
b100100 <
b10000000 P
b10011 )
b10011 0
b10011 C
b10011 L
b111 /
b100100 .
b100100 S
1(
#420000
0(
#425000
b1010010 1
b1010010 B
b1010010 K
b111 >
b100101 =
b100101 <
b10000000 P
b1010011 )
b1010011 0
b1010011 C
b1010011 L
b111 /
b100101 .
b100101 S
1(
#430000
0(
#435000
b110010 1
b110010 B
b110010 K
b111 >
b100110 =
b100110 <
b10000000 P
b110011 )
b110011 0
b110011 C
b110011 L
b111 /
b100110 .
b100110 S
1(
#440000
0(
#445000
b1110010 1
b1110010 B
b1110010 K
b111 >
b100111 =
b100111 <
b10000000 P
b1110011 )
b1110011 0
b1110011 C
b1110011 L
b111 /
b100111 .
b100111 S
1(
#450000
0(
#455000
b1010 1
b1010 B
b1010 K
b111 >
b101000 =
b101000 <
b10000000 P
b1011 )
b1011 0
b1011 C
b1011 L
b111 /
b101000 .
b101000 S
1(
#460000
0(
#465000
b1001010 1
b1001010 B
b1001010 K
b111 >
b101001 =
b101001 <
b10000000 P
b1001011 )
b1001011 0
b1001011 C
b1001011 L
b111 /
b101001 .
b101001 S
1(
#470000
0(
#475000
b101010 1
b101010 B
b101010 K
b111 >
b101010 =
b101010 <
b10000000 P
b101011 )
b101011 0
b101011 C
b101011 L
b111 /
b101010 .
b101010 S
1(
#480000
0(
#485000
b1101010 1
b1101010 B
b1101010 K
b111 >
b101011 =
b101011 <
b10000000 P
b1101011 )
b1101011 0
b1101011 C
b1101011 L
b111 /
b101011 .
b101011 S
1(
#490000
0(
#495000
b11010 1
b11010 B
b11010 K
b111 >
b101100 =
b101100 <
b10000000 P
b11011 )
b11011 0
b11011 C
b11011 L
b111 /
b101100 .
b101100 S
1(
#500000
0(
#505000
b1011010 1
b1011010 B
b1011010 K
b111 >
b101101 =
b101101 <
b10000000 P
b1011011 )
b1011011 0
b1011011 C
b1011011 L
b111 /
b101101 .
b101101 S
1(
#510000
0(
#515000
b111010 1
b111010 B
b111010 K
b111 >
b101110 =
b101110 <
b10000000 P
b111011 )
b111011 0
b111011 C
b111011 L
b111 /
b101110 .
b101110 S
1(
#520000
0(
#525000
b1111010 1
b1111010 B
b1111010 K
b111 >
b101111 =
b101111 <
b10000000 P
b1111011 )
b1111011 0
b1111011 C
b1111011 L
b111 /
b101111 .
b101111 S
1(
#530000
0(
#535000
b110 1
b110 B
b110 K
b111 >
b110000 =
b110000 <
b10000000 P
b111 )
b111 0
b111 C
b111 L
b111 /
b110000 .
b110000 S
1(
#540000
0(
#545000
b1000110 1
b1000110 B
b1000110 K
b111 >
b110001 =
b110001 <
b10000000 P
b1000111 )
b1000111 0
b1000111 C
b1000111 L
b111 /
b110001 .
b110001 S
1(
#550000
0(
#555000
b100110 1
b100110 B
b100110 K
b111 >
b110010 =
b110010 <
b10000000 P
b100111 )
b100111 0
b100111 C
b100111 L
b111 /
b110010 .
b110010 S
1(
#560000
0(
#565000
b1100110 1
b1100110 B
b1100110 K
b111 >
b110011 =
b110011 <
b10000000 P
b1100111 )
b1100111 0
b1100111 C
b1100111 L
b111 /
b110011 .
b110011 S
1(
#570000
0(
#575000
b10110 1
b10110 B
b10110 K
b111 >
b110100 =
b110100 <
b10000000 P
b10111 )
b10111 0
b10111 C
b10111 L
b111 /
b110100 .
b110100 S
1(
#580000
0(
#585000
b1010110 1
b1010110 B
b1010110 K
b111 >
b110101 =
b110101 <
b10000000 P
b1010111 )
b1010111 0
b1010111 C
b1010111 L
b111 /
b110101 .
b110101 S
1(
#590000
0(
#595000
b110110 1
b110110 B
b110110 K
b111 >
b110110 =
b110110 <
b10000000 P
b110111 )
b110111 0
b110111 C
b110111 L
b111 /
b110110 .
b110110 S
1(
#600000
0(
#605000
b1110110 1
b1110110 B
b1110110 K
b111 >
b110111 =
b110111 <
b10000000 P
b1110111 )
b1110111 0
b1110111 C
b1110111 L
b111 /
b110111 .
b110111 S
1(
#610000
0(
#615000
b1110 1
b1110 B
b1110 K
b111 >
b111000 =
b111000 <
b10000000 P
b1111 )
b1111 0
b1111 C
b1111 L
b111 /
b111000 .
b111000 S
1(
#620000
0(
#625000
b1001110 1
b1001110 B
b1001110 K
b111 >
b111001 =
b111001 <
b10000000 P
b1001111 )
b1001111 0
b1001111 C
b1001111 L
b111 /
b111001 .
b111001 S
1(
#630000
0(
#635000
b101110 1
b101110 B
b101110 K
b111 >
b111010 =
b111010 <
b10000000 P
b101111 )
b101111 0
b101111 C
b101111 L
b111 /
b111010 .
b111010 S
1(
#640000
0(
#645000
b1101110 1
b1101110 B
b1101110 K
b111 >
b111011 =
b111011 <
b10000000 P
b1101111 )
b1101111 0
b1101111 C
b1101111 L
b111 /
b111011 .
b111011 S
1(
#650000
0(
#655000
b11110 1
b11110 B
b11110 K
b111 >
b111100 =
b111100 <
b10000000 P
b11111 )
b11111 0
b11111 C
b11111 L
b111 /
b111100 .
b111100 S
1(
#660000
0(
#665000
b1011110 1
b1011110 B
b1011110 K
b111 >
b111101 =
b111101 <
b10000000 P
b1011111 )
b1011111 0
b1011111 C
b1011111 L
b111 /
b111101 .
b111101 S
1(
#670000
0(
#675000
b111110 1
b111110 B
b111110 K
b111 >
b111110 =
b111110 <
b10000000 P
b111111 )
b111111 0
b111111 C
b111111 L
b111 /
b111110 .
b111110 S
1(
#680000
0(
#685000
b1111110 1
b1111110 B
b1111110 K
b111 >
b111111 =
b111111 <
b10000000 P
b1111111 )
b1111111 0
b1111111 C
b1111111 L
b111 /
b111111 .
b111111 S
1(
#690000
0(
#695000
b1 1
b1 B
b1 K
b111 >
b1000000 =
b1000000 <
b10000000 P
b10 )
b10 0
b10 C
b10 L
b111 /
b1000000 .
b1000000 S
1(
#700000
0(
#705000
b1000001 1
b1000001 B
b1000001 K
b111 >
b1000001 =
b1000001 <
b10000000 P
b1000010 )
b1000010 0
b1000010 C
b1000010 L
b111 /
b1000001 .
b1000001 S
1(
#710000
0(
#715000
b100001 1
b100001 B
b100001 K
b111 >
b1000010 =
b1000010 <
b10000000 P
b100010 )
b100010 0
b100010 C
b100010 L
b111 /
b1000010 .
b1000010 S
1(
#720000
0(
#725000
b1100001 1
b1100001 B
b1100001 K
b111 >
b1000011 =
b1000011 <
b10000000 P
b1100010 )
b1100010 0
b1100010 C
b1100010 L
b111 /
b1000011 .
b1000011 S
1(
#730000
0(
#735000
b10001 1
b10001 B
b10001 K
b111 >
b1000100 =
b1000100 <
b10000000 P
b10010 )
b10010 0
b10010 C
b10010 L
b111 /
b1000100 .
b1000100 S
1(
#740000
0(
#745000
b1010001 1
b1010001 B
b1010001 K
b111 >
b1000101 =
b1000101 <
b10000000 P
b1010010 )
b1010010 0
b1010010 C
b1010010 L
b111 /
b1000101 .
b1000101 S
1(
#750000
0(
#755000
b110001 1
b110001 B
b110001 K
b111 >
b1000110 =
b1000110 <
b10000000 P
b110010 )
b110010 0
b110010 C
b110010 L
b111 /
b1000110 .
b1000110 S
1(
#760000
0(
#765000
b1110001 1
b1110001 B
b1110001 K
b111 >
b1000111 =
b1000111 <
b10000000 P
b1110010 )
b1110010 0
b1110010 C
b1110010 L
b111 /
b1000111 .
b1000111 S
1(
#770000
0(
#775000
b1001 1
b1001 B
b1001 K
b111 >
b1001000 =
b1001000 <
b10000000 P
b1010 )
b1010 0
b1010 C
b1010 L
b111 /
b1001000 .
b1001000 S
1(
#780000
0(
#785000
b1001001 1
b1001001 B
b1001001 K
b111 >
b1001001 =
b1001001 <
b10000000 P
b1001010 )
b1001010 0
b1001010 C
b1001010 L
b111 /
b1001001 .
b1001001 S
1(
#790000
0(
#795000
b101001 1
b101001 B
b101001 K
b111 >
b1001010 =
b1001010 <
b10000000 P
b101010 )
b101010 0
b101010 C
b101010 L
b111 /
b1001010 .
b1001010 S
1(
#800000
0(
#805000
b1101001 1
b1101001 B
b1101001 K
b111 >
b1001011 =
b1001011 <
b10000000 P
b1101010 )
b1101010 0
b1101010 C
b1101010 L
b111 /
b1001011 .
b1001011 S
1(
#810000
0(
#815000
b11001 1
b11001 B
b11001 K
b111 >
b1001100 =
b1001100 <
b10000000 P
b11010 )
b11010 0
b11010 C
b11010 L
b111 /
b1001100 .
b1001100 S
1(
#820000
0(
#825000
b1011001 1
b1011001 B
b1011001 K
b111 >
b1001101 =
b1001101 <
b10000000 P
b1011010 )
b1011010 0
b1011010 C
b1011010 L
b111 /
b1001101 .
b1001101 S
1(
#830000
0(
#835000
b111001 1
b111001 B
b111001 K
b111 >
b1001110 =
b1001110 <
b10000000 P
b111010 )
b111010 0
b111010 C
b111010 L
b111 /
b1001110 .
b1001110 S
1(
#840000
0(
#845000
b1111001 1
b1111001 B
b1111001 K
b111 >
b1001111 =
b1001111 <
b10000000 P
b1111010 )
b1111010 0
b1111010 C
b1111010 L
b111 /
b1001111 .
b1001111 S
1(
#850000
0(
#855000
b101 1
b101 B
b101 K
b111 >
b1010000 =
b1010000 <
b10000000 P
b110 )
b110 0
b110 C
b110 L
b111 /
b1010000 .
b1010000 S
1(
#860000
0(
#865000
b1000101 1
b1000101 B
b1000101 K
b111 >
b1010001 =
b1010001 <
b10000000 P
b1000110 )
b1000110 0
b1000110 C
b1000110 L
b111 /
b1010001 .
b1010001 S
1(
#870000
0(
#875000
b100101 1
b100101 B
b100101 K
b111 >
b1010010 =
b1010010 <
b10000000 P
b100110 )
b100110 0
b100110 C
b100110 L
b111 /
b1010010 .
b1010010 S
1(
#880000
0(
#885000
b1100101 1
b1100101 B
b1100101 K
b111 >
b1010011 =
b1010011 <
b10000000 P
b1100110 )
b1100110 0
b1100110 C
b1100110 L
b111 /
b1010011 .
b1010011 S
1(
#890000
0(
#895000
b10101 1
b10101 B
b10101 K
b111 >
b1010100 =
b1010100 <
b10000000 P
b10110 )
b10110 0
b10110 C
b10110 L
b111 /
b1010100 .
b1010100 S
1(
#900000
0(
#905000
b1010101 1
b1010101 B
b1010101 K
b111 >
b1010101 =
b1010101 <
b10000000 P
b1010110 )
b1010110 0
b1010110 C
b1010110 L
b111 /
b1010101 .
b1010101 S
1(
#910000
0(
#915000
b110101 1
b110101 B
b110101 K
b111 >
b1010110 =
b1010110 <
b10000000 P
b110110 )
b110110 0
b110110 C
b110110 L
b111 /
b1010110 .
b1010110 S
1(
#920000
0(
#925000
b1110101 1
b1110101 B
b1110101 K
b111 >
b1010111 =
b1010111 <
b10000000 P
b1110110 )
b1110110 0
b1110110 C
b1110110 L
b111 /
b1010111 .
b1010111 S
1(
#930000
0(
#935000
b1101 1
b1101 B
b1101 K
b111 >
b1011000 =
b1011000 <
b10000000 P
b1110 )
b1110 0
b1110 C
b1110 L
b111 /
b1011000 .
b1011000 S
1(
#940000
0(
#945000
b1001101 1
b1001101 B
b1001101 K
b111 >
b1011001 =
b1011001 <
b10000000 P
b1001110 )
b1001110 0
b1001110 C
b1001110 L
b111 /
b1011001 .
b1011001 S
1(
#950000
0(
#955000
b101101 1
b101101 B
b101101 K
b111 >
b1011010 =
b1011010 <
b10000000 P
b101110 )
b101110 0
b101110 C
b101110 L
b111 /
b1011010 .
b1011010 S
1(
#960000
0(
#965000
b1101101 1
b1101101 B
b1101101 K
b111 >
b1011011 =
b1011011 <
b10000000 P
b1101110 )
b1101110 0
b1101110 C
b1101110 L
b111 /
b1011011 .
b1011011 S
1(
#970000
0(
#975000
b11101 1
b11101 B
b11101 K
b111 >
b1011100 =
b1011100 <
b10000000 P
b11110 )
b11110 0
b11110 C
b11110 L
b111 /
b1011100 .
b1011100 S
1(
#980000
0(
