BitRevReorder.v
module BRR_PP #(
    parameter DATA_WIDTH = 8,
    parameter ADDR_WIDTH = 8
) (
    // Inputs
    input clk,
    input rst,
    input wr_en,
    input rd_en,
    input [DATA_WIDTH-1:0] data_in,

    // Outputs
    output [DATA_WIDTH-1:0] data_out,
    output reg buffer_full,
    output reg buffer_empty
);

    localparam DEPTH = 1 << ADDR_WIDTH;

    // Memory banks
    reg [DATA_WIDTH-1:0] mem_a [0:DEPTH-1];
    reg [DATA_WIDTH-1:0] mem_b [0:DEPTH-1];

    // Pointers for writing and reading
    reg [ADDR_WIDTH-1:0] write_counter;
    reg [ADDR_WIDTH-1:0] read_counter;

    // Bank selection signals
    reg wr_bank; // 0 for mem_a, 1 for mem_b
    reg rd_bank; // 0 for mem_a, 1 for mem_b

    // Write and read addresses
    wire [ADDR_WIDTH-1:0] wr_addr;
    wire [ADDR_WIDTH-1:0] rd_addr;


    // Function to reverse the bits of a vector
    function [ADDR_WIDTH-1:0] bit_reverse;
        input [ADDR_WIDTH-1:0] in;
        integer i;
        begin
            // Build the reversed-bit vector bit-by-bit
            for (i = 0; i < ADDR_WIDTH; i = i + 1)
                bit_reverse[i] = in[ADDR_WIDTH-1-i];
        end
    endfunction

    // Generate write address by bit-reversing the write_counter
    assign wr_addr = bit_reverse(write_counter);

    // Read address is the natural order read_counter
    assign rd_addr = read_counter;

    // Write logic
    always @(posedge clk) begin
        if (wr_en) begin
            if (wr_bank == 0)
                mem_a[wr_addr] <= data_in;
            else
                mem_b[wr_addr] <= data_in;
        end
    end

    // Counters and bank switching logic
    always @(posedge clk or posedge rst) begin
        if (rst) begin
            write_counter <= 0;
            read_counter  <= 0;
            wr_bank       <= 0;
            rd_bank       <= 1;
            buffer_full   <= 0;
            buffer_empty  <= 1;
        end else begin
            // Write counter logic and bank switching

            if (wr_en) begin
                if (write_counter == DEPTH - 1) begin
                    write_counter <= 0;
                    wr_bank       <= ~wr_bank; // Switch write bank
                    rd_bank       <= ~rd_bank; // force read bank switch: sync with write
                    buffer_full   <= 1;       // Signal that a buffer is full
                end else begin
                    write_counter <= write_counter + 1;
                    buffer_full   <= 0;
                end
            end

            // Read counter logic
            if (rd_en) begin
                if (read_counter == DEPTH - 1) begin
                    read_counter <= 0;
                    buffer_empty <= 1;      // Signal that a buffer is empty
                end else begin
                    read_counter <= read_counter + 1;
                    buffer_empty <= 0;
                end
            end

        end
    end

    // Output multiplexer
    assign data_out = (rd_bank == 0) ? mem_a[rd_addr] : mem_b[rd_addr];
    integer monitor_file;
    
    initial begin
        monitor_file = $fopen("monitor.txt", "w");
    end

    always @(posedge clk) begin
        $fdisplay(monitor_file, "Time=%0t | wr_en=%b rd_en=%b | wr_bank=%b rd_bank=%b | write_counter=%d read_counter=%d | write_addr=%d read_addr=%d | data_in=%d data_out=%d", 
                 $time, wr_en, rd_en, wr_bank, rd_bank, write_counter, read_counter, wr_addr, rd_addr, data_in, data_out);
    end
endmodule

brr_pp_tc/tb_BRR_PP.v
`timescale 1ns / 1ps

module tb_BRR_PP;

    // Parameters matching the DUT and verification script
    localparam ADDR_WIDTH = 7;
    localparam DATA_WIDTH = 16;
    localparam DEPTH      = 1 << ADDR_WIDTH; // Should be 128
    localparam CLK_PERIOD = 10;

    // Testbench signals
    reg                      clk;
    reg                      rst;
    reg                      wr_en;
    reg                      rd_en;
    reg  [DATA_WIDTH-1:0]    data_in;

    wire [DATA_WIDTH-1:0]    data_out;
    wire                     buffer_full;
    wire                     buffer_empty;

    // Instantiate the DUT (Device Under Test)
    BRR_PP #(
        .DATA_WIDTH(DATA_WIDTH),
        .ADDR_WIDTH(ADDR_WIDTH)
    ) DUT (
        .clk(clk),
        .rst(rst),
        .wr_en(wr_en),
        .rd_en(rd_en),
        .data_in(data_in),
        .data_out(data_out),
        .buffer_full(buffer_full),
        .buffer_empty(buffer_empty)
    );

    // Clock generation
    initial begin
        clk = 0;
        forever #(CLK_PERIOD/2) clk = ~clk;
    end

    // Main stimulus block
    initial begin
        // 1. Initialize and Reset
        $display("Starting testbench...");
        rst = 1;
        wr_en = 0;
        rd_en = 0;
        data_in = 0;
        #(CLK_PERIOD * 5);
        rst = 0;
        #(CLK_PERIOD);

        // Wait for reset to de-assert
        @(posedge clk);
        $display("Reset released. Starting data transmission.");

        // 2. Write the first frame of data (to Buffer A)
        $display("Writing Frame 0...");
        write_frame(0);

        // After writing, the 'other' buffer is now ready for reading.
        // We must wait one cycle for the read address to be registered.
        @(posedge clk);

        // 3. Simultaneously READ Frame 0 (from Buffer A) and WRITE Frame 1 (to Buffer B)
        $display("Concurrently Reading Frame 0 and Writing Frame 1...");
        fork
            read_frame();
            write_frame(1);
        join
        
        // Wait one cycle for read address to be registered.
        @(posedge clk);

        // 4. Read the second frame of data (from Buffer B)
        $display("Reading Frame 1...");
        read_frame();

        // End of test
        #(CLK_PERIOD * 10);
        $display("Test finished.");
        $finish;
    end

    function [ADDR_WIDTH-1:0] bit_reverse;
        input [ADDR_WIDTH-1:0] in;
        integer i;
        begin
            for (i = 0; i < ADDR_WIDTH; i = i + 1)
                bit_reverse[i] = in[ADDR_WIDTH-1-i];
        end
    endfunction

    // Task to write one frame of data
    task write_frame;

        
        input integer frame_num;
        integer i;
        begin
            wr_en = 1;
            #CLK_PERIOD;
            for (i = 0; i < DEPTH; i = i + 1) begin
                
                // Send sequential data values
                data_in = bit_reverse(i) + frame_num * DEPTH;
                #CLK_PERIOD;
            end
            @(posedge clk);
            wr_en = 0;
        end
    endtask

    // Task to read one frame of data
    task read_frame;
        integer i;
        begin
            for (i = 0; i < DEPTH; i = i + 1) begin
                @(posedge clk);
                rd_en = 1;
            end
            @(posedge clk);
            rd_en = 0;
        end
    endtask

    // Monitor: Save output data to a file for verification
    integer outfile;
    initial begin
        // Setup simulation dump
        $dumpfile("tb_brr_pp.vcd");
        $dumpvars(0, tb_BRR_PP);

        // Open file for output
        outfile = $fopen("output.txt", "w");
        
        // Forever loop to monitor the output
        forever @(posedge clk) begin
            // Data is valid on the cycle that rd_en is high
            if (rd_en) begin
                #CLK_PERIOD; // Wait for data_out to stabilize
                $fdisplay(outfile, "%d %d", data_out, 0);
            end
        end
    end

endmodule

brr_pp_tc/tb_brr_pp.vcd
$date
	Sat Oct 25 01:14:51 2025
$end
$version
	Icarus Verilog
$end
$timescale
	1ps
$end
$scope module tb_BRR_PP $end
$var wire 16 ! data_out [15:0] $end
$var wire 1 " buffer_full $end
$var wire 1 # buffer_empty $end
$var parameter 32 $ ADDR_WIDTH $end
$var parameter 32 % CLK_PERIOD $end
$var parameter 32 & DATA_WIDTH $end
$var parameter 39 ' DEPTH $end
$var reg 1 ( clk $end
$var reg 16 ) data_in [15:0] $end
$var reg 1 * rd_en $end
$var reg 1 + rst $end
$var reg 1 , wr_en $end
$var integer 32 - outfile [31:0] $end
$scope function bit_reverse $end
$var reg 7 . in [6:0] $end
$var integer 32 / i [31:0] $end
$upscope $end
$scope module DUT $end
$var wire 1 ( clk $end
$var wire 16 0 data_in [15:0] $end
$var wire 1 * rd_en $end
$var wire 1 + rst $end
$var wire 1 , wr_en $end
$var wire 7 1 wr_addr [6:0] $end
$var wire 7 2 rd_addr [6:0] $end
$var wire 16 3 data_out [15:0] $end
$var parameter 32 4 ADDR_WIDTH $end
$var parameter 32 5 DATA_WIDTH $end
$var parameter 39 6 DEPTH $end
$var reg 1 # buffer_empty $end
$var reg 1 " buffer_full $end
$var reg 1 7 rd_bank $end
$var reg 7 8 read_counter [6:0] $end
$var reg 1 9 wr_bank $end
$var reg 7 : write_counter [6:0] $end
$var integer 32 ; monitor_file [31:0] $end
$scope function bit_reverse $end
$var reg 7 < in [6:0] $end
$var integer 32 = i [31:0] $end
$upscope $end
$upscope $end
$scope task read_frame $end
$var integer 32 > i [31:0] $end
$upscope $end
$scope task write_frame $end
$var integer 32 ? frame_num [31:0] $end
$var integer 32 @ i [31:0] $end
$upscope $end
$upscope $end
$enddefinitions $end
$comment Show the parameter values. $end
$dumpall
b10000000 6
b10000 5
b111 4
b10000000 '
b10000 &
b1010 %
b111 $
$end
#0
$dumpvars
bx @
bx ?
bx >
b111 =
b0 <
b10000000000000000000000000000011 ;
b0 :
09
b0 8
17
bx 3
b0 2
b0 1
b0 0
bx /
bx .
b10000000000000000000000000000100 -
0,
1+
0*
b0 )
0(
1#
0"
bx !
$end
#5000
1(
#10000
0(
#15000
1(
#20000
0(
#25000
1(
#30000
0(
#35000
1(
#40000
0(
#45000
1(
#50000
0(
0+
#55000
1(
#60000
0(
#65000
1,
b0 ?
1(
#70000
0(
#75000
b1000000 1
b111 =
b1 <
b1 :
1(
b111 /
b0 .
b0 @
#80000
0(
#85000
b100000 1
b111 =
b10 <
b10 :
1(
b1000000 )
b1000000 0
b111 /
b1 .
b1 @
#90000
0(
#95000
b1100000 1
b111 =
b11 <
b11 :
1(
b100000 )
b100000 0
b111 /
b10 .
b10 @
#100000
0(
#105000
b10000 1
b111 =
b100 <
b100 :
1(
b1100000 )
b1100000 0
b111 /
b11 .
b11 @
#110000
0(
#115000
b1010000 1
b111 =
b101 <
b101 :
1(
b10000 )
b10000 0
b111 /
b100 .
b100 @
#120000
0(
#125000
b110000 1
b111 =
b110 <
b110 :
1(
b1010000 )
b1010000 0
b111 /
b101 .
b101 @
#130000
0(
#135000
b1110000 1
b111 =
b111 <
b111 :
1(
b110000 )
b110000 0
b111 /
b110 .
b110 @
#140000
0(
#145000
b1000 1
b111 =
b1000 <
b1000 :
1(
b1110000 )
b1110000 0
b111 /
b111 .
b111 @
#150000
0(
#155000
b1001000 1
b111 =
b1001 <
b1001 :
1(
b1000 )
b1000 0
b111 /
b1000 .
b1000 @
#160000
0(
#165000
b101000 1
b111 =
b1010 <
b1010 :
1(
b1001000 )
b1001000 0
b111 /
b1001 .
b1001 @
#170000
0(
#175000
b1101000 1
b111 =
b1011 <
b1011 :
1(
b101000 )
b101000 0
b111 /
b1010 .
b1010 @
#180000
0(
#185000
b11000 1
b111 =
b1100 <
b1100 :
1(
b1101000 )
b1101000 0
b111 /
b1011 .
b1011 @
#190000
0(
#195000
b1011000 1
b111 =
b1101 <
b1101 :
1(
b11000 )
b11000 0
b111 /
b1100 .
b1100 @
#200000
0(
#205000
b111000 1
b111 =
b1110 <
b1110 :
1(
b1011000 )
b1011000 0
b111 /
b1101 .
b1101 @
#210000
0(
#215000
b1111000 1
b111 =
b1111 <
b1111 :
1(
b111000 )
b111000 0
b111 /
b1110 .
b1110 @
#220000
0(
#225000
b100 1
b111 =
b10000 <
b10000 :
1(
b1111000 )
b1111000 0
b111 /
b1111 .
b1111 @
#230000
0(
#235000
b1000100 1
b111 =
b10001 <
b10001 :
1(
b100 )
b100 0
b111 /
b10000 .
b10000 @
#240000
0(
#245000
b100100 1
b111 =
b10010 <
b10010 :
1(
b1000100 )
b1000100 0
b111 /
b10001 .
b10001 @
#250000
0(
#255000
b1100100 1
b111 =
b10011 <
b10011 :
1(
b100100 )
b100100 0
b111 /
b10010 .
b10010 @
#260000
0(
#265000
b10100 1
b111 =
b10100 <
b10100 :
1(
b1100100 )
b1100100 0
b111 /
b10011 .
b10011 @
#270000
0(
#275000
b1010100 1
b111 =
b10101 <
b10101 :
1(
b10100 )
b10100 0
b111 /
b10100 .
b10100 @
#280000
0(
#285000
b110100 1
b111 =
b10110 <
b10110 :
1(
b1010100 )
b1010100 0
b111 /
b10101 .
b10101 @
#290000
0(
#295000
b1110100 1
b111 =
b10111 <
b10111 :
1(
b110100 )
b110100 0
b111 /
b10110 .
b10110 @
#300000
0(
#305000
b1100 1
b111 =
b11000 <
b11000 :
1(
b1110100 )
b1110100 0
b111 /
b10111 .
b10111 @
#310000
0(
#315000
b1001100 1
b111 =
b11001 <
b11001 :
1(
b1100 )
b1100 0
b111 /
b11000 .
b11000 @
#320000
0(
#325000
b101100 1
b111 =
b11010 <
b11010 :
1(
b1001100 )
b1001100 0
b111 /
b11001 .
b11001 @
#330000
0(
#335000
b1101100 1
b111 =
b11011 <
b11011 :
1(
b101100 )
b101100 0
b111 /
b11010 .
b11010 @
#340000
0(
#345000
b11100 1
b111 =
b11100 <
b11100 :
1(
b1101100 )
b1101100 0
b111 /
b11011 .
b11011 @
#350000
0(
#355000
b1011100 1
b111 =
b11101 <
b11101 :
1(
b11100 )
b11100 0
b111 /
b11100 .
b11100 @
#360000
0(
#365000
b111100 1
b111 =
b11110 <
b11110 :
1(
b1011100 )
b1011100 0
b111 /
b11101 .
b11101 @
#370000
0(
#375000
b1111100 1
b111 =
b11111 <
b11111 :
1(
b111100 )
b111100 0
b111 /
b11110 .
b11110 @
#380000
0(
#385000
b10 1
b111 =
b100000 <
b100000 :
1(
b1111100 )
b1111100 0
b111 /
b11111 .
b11111 @
#390000
0(
#395000
b1000010 1
b111 =
b100001 <
b100001 :
1(
b10 )
b10 0
b111 /
b100000 .
b100000 @
#400000
0(
#405000
b100010 1
b111 =
b100010 <
b100010 :
1(
b1000010 )
b1000010 0
b111 /
b100001 .
b100001 @
#410000
0(
#415000
b1100010 1
b111 =
b100011 <
b100011 :
1(
b100010 )
b100010 0
b111 /
b100010 .
b100010 @
#420000
0(
#425000
b10010 1
b111 =
b100100 <
b100100 :
1(
b1100010 )
b1100010 0
b111 /
b100011 .
b100011 @
#430000
0(
#435000
b1010010 1
b111 =
b100101 <
b100101 :
1(
b10010 )
b10010 0
b111 /
b100100 .
b100100 @
#440000
0(
#445000
b110010 1
b111 =
b100110 <
b100110 :
1(
b1010010 )
b1010010 0
b111 /
b100101 .
b100101 @
#450000
0(
#455000
b1110010 1
b111 =
b100111 <
b100111 :
1(
b110010 )
b110010 0
b111 /
b100110 .
b100110 @
#460000
0(
#465000
b1010 1
b111 =
b101000 <
b101000 :
1(
b1110010 )
b1110010 0
b111 /
b100111 .
b100111 @
#470000
0(
#475000
b1001010 1
b111 =
b101001 <
b101001 :
1(
b1010 )
b1010 0
b111 /
b101000 .
b101000 @
#480000
0(
#485000
b101010 1
b111 =
b101010 <
b101010 :
1(
b1001010 )
b1001010 0
b111 /
b101001 .
b101001 @
#490000
0(
#495000
b1101010 1
b111 =
b101011 <
b101011 :
1(
b101010 )
b101010 0
b111 /
b101010 .
b101010 @
#500000
0(
#505000
b11010 1
b111 =
b101100 <
b101100 :
1(
b1101010 )
b1101010 0
b111 /
b101011 .
b101011 @
#510000
0(
#515000
b1011010 1
b111 =
b101101 <
b101101 :
1(
b11010 )
b11010 0
b111 /
b101100 .
b101100 @
#520000
0(
#525000
b111010 1
b111 =
b101110 <
b101110 :
1(
b1011010 )
b1011010 0
b111 /
b101101 .
b101101 @
#530000
0(
#535000
b1111010 1
b111 =
b101111 <
b101111 :
1(
b111010 )
b111010 0
b111 /
b101110 .
b101110 @
#540000
0(
#545000
b110 1
b111 =
b110000 <
b110000 :
1(
b1111010 )
b1111010 0
b111 /
b101111 .
b101111 @
#550000
0(
#555000
b1000110 1
b111 =
b110001 <
b110001 :
1(
b110 )
b110 0
b111 /
b110000 .
b110000 @
#560000
0(
#565000
b100110 1
b111 =
b110010 <
b110010 :
1(
b1000110 )
b1000110 0
b111 /
b110001 .
b110001 @
#570000
0(
#575000
b1100110 1
b111 =
b110011 <
b110011 :
1(
b100110 )
b100110 0
b111 /
b110010 .
b110010 @
#580000
0(
#585000
b10110 1
b111 =
b110100 <
b110100 :
1(
b1100110 )
b1100110 0
b111 /
b110011 .
b110011 @
#590000
0(
#595000
b1010110 1
b111 =
b110101 <
b110101 :
1(
b10110 )
b10110 0
b111 /
b110100 .
b110100 @
#600000
0(
#605000
b110110 1
b111 =
b110110 <
b110110 :
1(
b1010110 )
b1010110 0
b111 /
b110101 .
b110101 @
#610000
0(
#615000
b1110110 1
b111 =
b110111 <
b110111 :
1(
b110110 )
b110110 0
b111 /
b110110 .
b110110 @
#620000
0(
#625000
b1110 1
b111 =
b111000 <
b111000 :
1(
b1110110 )
b1110110 0
b111 /
b110111 .
b110111 @
#630000
0(
#635000
b1001110 1
b111 =
b111001 <
b111001 :
1(
b1110 )
b1110 0
b111 /
b111000 .
b111000 @
#640000
0(
#645000
b101110 1
b111 =
b111010 <
b111010 :
1(
b1001110 )
b1001110 0
b111 /
b111001 .
b111001 @
#650000
0(
#655000
b1101110 1
b111 =
b111011 <
b111011 :
1(
b101110 )
b101110 0
b111 /
b111010 .
b111010 @
#660000
0(
#665000
b11110 1
b111 =
b111100 <
b111100 :
1(
b1101110 )
b1101110 0
b111 /
b111011 .
b111011 @
#670000
0(
#675000
b1011110 1
b111 =
b111101 <
b111101 :
1(
b11110 )
b11110 0
b111 /
b111100 .
b111100 @
#680000
0(
#685000
b111110 1
b111 =
b111110 <
b111110 :
1(
b1011110 )
b1011110 0
b111 /
b111101 .
b111101 @
#690000
0(
#695000
b1111110 1
b111 =
b111111 <
b111111 :
1(
b111110 )
b111110 0
b111 /
b111110 .
b111110 @
#700000
0(
#705000
b1 1
b111 =
b1000000 <
b1000000 :
1(
b1111110 )
b1111110 0
b111 /
b111111 .
b111111 @
#710000
0(
#715000
b1000001 1
b111 =
b1000001 <
b1000001 :
1(
b1 )
b1 0
b111 /
b1000000 .
b1000000 @
#720000
0(
#725000
b100001 1
b111 =
b1000010 <
b1000010 :
1(
b1000001 )
b1000001 0
b111 /
b1000001 .
b1000001 @
#730000
0(
#735000
b1100001 1
b111 =
b1000011 <
b1000011 :
1(
b100001 )
b100001 0
b111 /
b1000010 .
b1000010 @
#740000
0(
#745000
b10001 1
b111 =
b1000100 <
b1000100 :
1(
b1100001 )
b1100001 0
b111 /
b1000011 .
b1000011 @
#750000
0(
#755000
b1010001 1
b111 =
b1000101 <
b1000101 :
1(
b10001 )
b10001 0
b111 /
b1000100 .
b1000100 @
#760000
0(
#765000
b110001 1
b111 =
b1000110 <
b1000110 :
1(
b1010001 )
b1010001 0
b111 /
b1000101 .
b1000101 @
#770000
0(
#775000
b1110001 1
b111 =
b1000111 <
b1000111 :
1(
b110001 )
b110001 0
b111 /
b1000110 .
b1000110 @
#780000
0(
#785000
b1001 1
b111 =
b1001000 <
b1001000 :
1(
b1110001 )
b1110001 0
b111 /
b1000111 .
b1000111 @
#790000
0(
#795000
b1001001 1
b111 =
b1001001 <
b1001001 :
1(
b1001 )
b1001 0
b111 /
b1001000 .
b1001000 @
#800000
0(
#805000
b101001 1
b111 =
b1001010 <
b1001010 :
1(
b1001001 )
b1001001 0
b111 /
b1001001 .
b1001001 @
#810000
0(
#815000
b1101001 1
b111 =
b1001011 <
b1001011 :
1(
b101001 )
b101001 0
b111 /
b1001010 .
b1001010 @
#820000
0(
#825000
b11001 1
b111 =
b1001100 <
b1001100 :
1(
b1101001 )
b1101001 0
b111 /
b1001011 .
b1001011 @
#830000
0(
#835000
b1011001 1
b111 =
b1001101 <
b1001101 :
1(
b11001 )
b11001 0
b111 /
b1001100 .
b1001100 @
#840000
0(
#845000
b111001 1
b111 =
b1001110 <
b1001110 :
1(
b1011001 )
b1011001 0
b111 /
b1001101 .
b1001101 @
#850000
0(
#855000
b1111001 1
b111 =
b1001111 <
b1001111 :
1(
b111001 )
b111001 0
b111 /
b1001110 .
b1001110 @
#860000
0(
#865000
b101 1
b111 =
b1010000 <
b1010000 :
1(
b1111001 )
b1111001 0
b111 /
b1001111 .
b1001111 @
#870000
0(
#875000
b1000101 1
b111 =
b1010001 <
b1010001 :
1(
b101 )
b101 0
b111 /
b1010000 .
b1010000 @
#880000
0(
#885000
b100101 1
b111 =
b1010010 <
b1010010 :
1(
b1000101 )
b1000101 0
b111 /
b1010001 .
b1010001 @
#890000
0(
#895000
b1100101 1
b111 =
b1010011 <
b1010011 :
1(
b100101 )
b100101 0
b111 /
b1010010 .
b1010010 @
#900000
0(
#905000
b10101 1
b111 =
b1010100 <
b1010100 :
1(
b1100101 )
b1100101 0
b111 /
b1010011 .
b1010011 @
#910000
0(
#915000
b1010101 1
b111 =
b1010101 <
b1010101 :
1(
b10101 )
b10101 0
b111 /
b1010100 .
b1010100 @
#920000
0(
#925000
b110101 1
b111 =
b1010110 <
b1010110 :
1(
b1010101 )
b1010101 0
b111 /
b1010101 .
b1010101 @
#930000
0(
#935000
b1110101 1
b111 =
b1010111 <
b1010111 :
1(
b110101 )
b110101 0
b111 /
b1010110 .
b1010110 @
#940000
0(
#945000
b1101 1
b111 =
b1011000 <
b1011000 :
1(
b1110101 )
b1110101 0
b111 /
b1010111 .
b1010111 @
#950000
0(
#955000
b1001101 1
b111 =
b1011001 <
b1011001 :
1(
b1101 )
b1101 0
b111 /
b1011000 .
b1011000 @
#960000
0(
#965000
b101101 1
b111 =
b1011010 <
b1011010 :
1(
b1001101 )
b1001101 0
b111 /
b1011001 .
b1011001 @
#970000
0(
#975000
b1101101 1
b111 =
b1011011 <
b1011011 :
1(
b101101 )
b101101 0
b111 /
b1011010 .
b1011010 @
#980000
0(
#985000
b11101 1
b111 =
b1011100 <
b1011100 :
1(
b1101101 )
b1101101 0
b111 /
b1011011 .
b1011011 @
#990000
0(
#995000
b1011101 1
b111 =
b1011101 <
b1011101 :
1(
b11101 )
b11101 0
b111 /
b1011100 .
b1011100 @
#1000000
0(
#1005000
b111101 1
b111 =
b1011110 <
b1011110 :
1(
b1011101 )
b1011101 0
b111 /
b1011101 .
b1011101 @
#1010000
0(
#1015000
b1111101 1
b111 =
b1011111 <
b1011111 :
1(
b111101 )
b111101 0
b111 /
b1011110 .
b1011110 @
#1020000
0(
#1025000
b11 1
b111 =
b1100000 <
b1100000 :
1(
b1111101 )
b1111101 0
b111 /
b1011111 .
b1011111 @
#1030000
0(
#1035000
b1000011 1
b111 =
b1100001 <
b1100001 :
1(
b11 )
b11 0
b111 /
b1100000 .
b1100000 @
#1040000
0(
#1045000
b100011 1
b111 =
b1100010 <
b1100010 :
1(
b1000011 )
b1000011 0
b111 /
b1100001 .
b1100001 @
#1050000
0(
#1055000
b1100011 1
b111 =
b1100011 <
b1100011 :
1(
b100011 )
b100011 0
b111 /
b1100010 .
b1100010 @
#1060000
0(
#1065000
b10011 1
b111 =
b1100100 <
b1100100 :
1(
b1100011 )
b1100011 0
b111 /
b1100011 .
b1100011 @
#1070000
0(
#1075000
b1010011 1
b111 =
b1100101 <
b1100101 :
1(
b10011 )
b10011 0
b111 /
b1100100 .
b1100100 @
#1080000
0(
#1085000
b110011 1
b111 =
b1100110 <
b1100110 :
1(
b1010011 )
b1010011 0
b111 /
b1100101 .
b1100101 @
#1090000
0(
#1095000
b1110011 1
b111 =
b1100111 <
b1100111 :
1(
b110011 )
b110011 0
b111 /
b1100110 .
b1100110 @
#1100000
0(
#1105000
b1011 1
b111 =
b1101000 <
b1101000 :
1(
b1110011 )
b1110011 0
b111 /
b1100111 .
b1100111 @
#1110000
0(
#1115000
b1001011 1
b111 =
b1101001 <
b1101001 :
1(
b1011 )
b1011 0
b111 /
b1101000 .
b1101000 @
#1120000
0(
#1125000
b101011 1
b111 =
b1101010 <
b1101010 :
1(
b1001011 )
b1001011 0
b111 /
b1101001 .
b1101001 @
#1130000
0(
#1135000
b1101011 1
b111 =
b1101011 <
b1101011 :
1(
b101011 )
b101011 0
b111 /
b1101010 .
b1101010 @
#1140000
0(
#1145000
b11011 1
b111 =
b1101100 <
b1101100 :
1(
b1101011 )
b1101011 0
b111 /
b1101011 .
b1101011 @
#1150000
0(
#1155000
b1011011 1
b111 =
b1101101 <
b1101101 :
1(
b11011 )
b11011 0
b111 /
b1101100 .
b1101100 @
#1160000
0(
#1165000
b111011 1
b111 =
b1101110 <
b1101110 :
1(
b1011011 )
b1011011 0
b111 /
b1101101 .
b1101101 @
#1170000
0(
#1175000
b1111011 1
b111 =
b1101111 <
b1101111 :
1(
b111011 )
b111011 0
b111 /
b1101110 .
b1101110 @
#1180000
0(
#1185000
b111 1
b111 =
b1110000 <
b1110000 :
1(
b1111011 )
b1111011 0
b111 /
b1101111 .
b1101111 @
#1190000
0(
#1195000
b1000111 1
b111 =
b1110001 <
b1110001 :
1(
b111 )
b111 0
b111 /
b1110000 .
b1110000 @
#1200000
0(
#1205000
b100111 1
b111 =
b1110010 <
b1110010 :
1(
b1000111 )
b1000111 0
b111 /
b1110001 .
b1110001 @
#1210000
0(
#1215000
b1100111 1
b111 =
b1110011 <
b1110011 :
1(
b100111 )
b100111 0
b111 /
b1110010 .
b1110010 @
#1220000
0(
#1225000
b10111 1
b111 =
b1110100 <
b1110100 :
1(
b1100111 )
b1100111 0
b111 /
b1110011 .
b1110011 @
#1230000
0(
#1235000
b1010111 1
b111 =
b1110101 <
b1110101 :
1(
b10111 )
b10111 0
b111 /
b1110100 .
b1110100 @
#1240000
0(
#1245000
b110111 1
b111 =
b1110110 <
b1110110 :
1(
b1010111 )
b1010111 0
b111 /
b1110101 .
b1110101 @
#1250000
0(
#1255000
b1110111 1
b111 =
b1110111 <
b1110111 :
1(
b110111 )
b110111 0
b111 /
b1110110 .
b1110110 @
#1260000
0(
#1265000
b1111 1
b111 =
b1111000 <
b1111000 :
1(
b1110111 )
b1110111 0
b111 /
b1110111 .
b1110111 @
#1270000
0(
#1275000
b1001111 1
b111 =
b1111001 <
b1111001 :
1(
b1111 )
b1111 0
b111 /
b1111000 .
b1111000 @
#1280000
0(
#1285000
b101111 1
b111 =
b1111010 <
b1111010 :
1(
b1001111 )
b1001111 0
b111 /
b1111001 .
b1111001 @
#1290000
0(
#1295000
b1101111 1
b111 =
b1111011 <
b1111011 :
1(
b101111 )
b101111 0
b111 /
b1111010 .
b1111010 @
#1300000
0(
#1305000
b11111 1
b111 =
b1111100 <
b1111100 :
1(
b1101111 )
b1101111 0
b111 /
b1111011 .
b1111011 @
#1310000
0(
#1315000
b1011111 1
b111 =
b1111101 <
b1111101 :
1(
b11111 )
b11111 0
b111 /
b1111100 .
b1111100 @
#1320000
0(
#1325000
b111111 1
b111 =
b1111110 <
b1111110 :
1(
b1011111 )
b1011111 0
b111 /
b1111101 .
b1111101 @
#1330000
0(
#1335000
b1111111 1
b111 =
b1111111 <
b1111111 :
1(
b111111 )
b111111 0
b111 /
b1111110 .
b1111110 @
#1340000
0(
#1345000
b0 !
b0 3
b0 1
b111 =
b0 <
1"
07
19
b0 :
1(
b1111111 )
b1111111 0
b111 /
b1111111 .
b1111111 @
#1350000
0(
#1355000
b1000000 1
b111 =
b1 <
0"
b1 :
0,
1(
b10000000 @
#1360000
0(
#1365000
b0 >
1,
b1 ?
1(
#1370000
0(
#1375000
b100000 1
b111 =
b10 <
b10 :
b1 >
1*
1(
b10000000 )
b10000000 0
b111 /
b0 .
b0 @
#1380000
0(
#1385000
b1 !
b1 3
b1100000 1
b111 =
b11 <
0#
b1 2
b1 8
b11 :
b10 >
1(
b11000000 )
b11000000 0
b111 /
b1 .
b1 @
#1390000
0(
#1395000
b10 !
b10 3
b10000 1
b111 =
b100 <
b10 2
b10 8
b100 :
b11 >
1(
b10100000 )
b10100000 0
b111 /
b10 .
b10 @
#1400000
0(
#1405000
b11 !
b11 3
b1010000 1
b111 =
b101 <
b11 2
b11 8
b101 :
b100 >
1(
b11100000 )
b11100000 0
b111 /
b11 .
b11 @
#1410000
0(
#1415000
b100 !
b100 3
b110000 1
b111 =
b110 <
b100 2
b100 8
b110 :
b101 >
1(
b10010000 )
b10010000 0
b111 /
b100 .
b100 @
#1420000
0(
#1425000
b101 !
b101 3
b1110000 1
b111 =
b111 <
b101 2
b101 8
b111 :
b110 >
1(
b11010000 )
b11010000 0
b111 /
b101 .
b101 @
#1430000
0(
#1435000
b110 !
b110 3
b1000 1
b111 =
b1000 <
b110 2
b110 8
b1000 :
b111 >
1(
b10110000 )
b10110000 0
b111 /
b110 .
b110 @
#1440000
0(
#1445000
b111 !
b111 3
b1001000 1
b111 =
b1001 <
b111 2
b111 8
b1001 :
b1000 >
1(
b11110000 )
b11110000 0
b111 /
b111 .
b111 @
#1450000
0(
#1455000
b1000 !
b1000 3
b101000 1
b111 =
b1010 <
b1000 2
b1000 8
b1010 :
b1001 >
1(
b10001000 )
b10001000 0
b111 /
b1000 .
b1000 @
#1460000
0(
#1465000
b1001 !
b1001 3
b1101000 1
b111 =
b1011 <
b1001 2
b1001 8
b1011 :
b1010 >
1(
b11001000 )
b11001000 0
b111 /
b1001 .
b1001 @
#1470000
0(
#1475000
b1010 !
b1010 3
b11000 1
b111 =
b1100 <
b1010 2
b1010 8
b1100 :
b1011 >
1(
b10101000 )
b10101000 0
b111 /
b1010 .
b1010 @
#1480000
0(
#1485000
b1011 !
b1011 3
b1011000 1
b111 =
b1101 <
b1011 2
b1011 8
b1101 :
b1100 >
1(
b11101000 )
b11101000 0
b111 /
b1011 .
b1011 @
#1490000
0(
#1495000
b1100 !
b1100 3
b111000 1
b111 =
b1110 <
b1100 2
b1100 8
b1110 :
b1101 >
1(
b10011000 )
b10011000 0
b111 /
b1100 .
b1100 @
#1500000
0(
#1505000
b1101 !
b1101 3
b1111000 1
b111 =
b1111 <
b1101 2
b1101 8
b1111 :
b1110 >
1(
b11011000 )
b11011000 0
b111 /
b1101 .
b1101 @
#1510000
0(
#1515000
b1110 !
b1110 3
b100 1
b111 =
b10000 <
b1110 2
b1110 8
b10000 :
b1111 >
1(
b10111000 )
b10111000 0
b111 /
b1110 .
b1110 @
#1520000
0(
#1525000
b1111 !
b1111 3
b1000100 1
b111 =
b10001 <
b1111 2
b1111 8
b10001 :
b10000 >
1(
b11111000 )
b11111000 0
b111 /
b1111 .
b1111 @
#1530000
0(
#1535000
b10000 !
b10000 3
b100100 1
b111 =
b10010 <
b10000 2
b10000 8
b10010 :
b10001 >
1(
b10000100 )
b10000100 0
b111 /
b10000 .
b10000 @
#1540000
0(
